Workbook
Name CLASS: #REF!
Name CLASS: #REF!
Name CLASS: #REF!
Name CLASS: #REF!
Name CLASS: #REF!
Name CODE: #REF!
Name CODE: #REF!
Name CODE: #REF!
Name CODE: #REF!
Name CODE: #REF!
Name CODE: #REF!
Name CODE: #REF!
Name CODE: #REF!
Name COURSE_NAME: #REF!
Name COURSE_NAME: #REF!
Name COURSE_NAME: #REF!
Name COURSE_NAME: #REF!
Name COURSE_NAME: #REF!
Name COURSE_NAME: #REF!
Name COURSE_NAME: #REF!
Name COURSE_NAME: #REF!
Name EA: #REF!
Name EXAMINER: #REF!
Name EXAMINER: #REF!
Name EXAMINER: #REF!
Name EXAMINER: #REF!
Name EXAMINER: #REF!
Name EXAMINER: #REF!
Name EXAMINER: #REF!
Name EXAMINER: #REF!
Name hy: #REF!
Name hy: #REF!
Name po: #REF!
Name po: #REF!
Name room_no: #REF!
Name room_no: #REF!
Name room_no: #REF!
Name ROOM_NO.: #REF!
Name ROOM_NO.: #REF!
Name ROOM_NO.: #REF!
Name ROOM_NO.: #REF!
Name ROOM_NO.: #REF!
Name ROOM_NO.: #REF!
Name ROOM_NO.: #REF!
Name STDS: #REF!
Name STDS: #REF!
Name STDS: #REF!
Name STDS: #REF!
Name STDS: #REF!
Name STDS: #REF!
Name STDS: #REF!
Name STDS: #REF!
Name TO_PRT: #REF!
Name TO_PRT: #REF!
Name TO_PRT: #REF!
Name TO_PRT: #REF!
Name TO_PRT: #REF!
Name TO_PRT: #REF!
Name TO_PRT: #REF!
Name TO_PRT: #REF!

Sheet TT
I1: =_xlfn.CONCAT(A1,",",D1) -> , | J1: =#N/A -> #N/A
I2: , | J2: =#N/A -> #N/A
A3: Tuesday, 7 April 2026 | I3: Tuesday, 7 April 2026, | J3: =#N/A -> #N/A
A4: Session, 1 (8:30 AM - 10:30 AM) | I4: Session, 1 (8:30 AM - 10:30 AM), | J4: =#N/A -> #N/A
A5: CODE | B5: COURSE NAME | C5: EXAMINER | D5: CLASS | E5: # STDS | F5: ROOM NO. | G5: TO PRT | I5: CODE ,CLASS | J5: =#N/A -> #N/A
A6: MATH 251 | B6: =IFERROR(VLOOKUP(I6:I15,Lecturers!A2:F596,6,FALSE),0) -> DIFFERENTIAL EQUATIONS | C6: =IFERROR(VLOOKUP(I6:I15,Lecturers!A2:F596,2,FALSE),0) -> Boateng Maxwell Akwasi | D6: ED2-MARI | E6: =IFERROR(VLOOKUP(I6:I15,Lecturers!A2:F596,3,FALSE),0) -> 37 | F6: NAF1 | G6: =E6*1.1 -> 40.7 | H6: 37 | I6: =_xlfn.CONCAT(A6,",",D6) -> MATH 251,ED2-MARI | J6: 74
A7: MATH 251 | B7: DIFFERENTIAL EQUATIONS | C7: Boateng Maxwell Akwasi | D7: ED2-ME | E7: 242 | F7: NEB-TF/NEB-SF/NEB-FF1/NEB-FF2 | G7: =E7*1.1 -> 266.2 | H7: 80/80/52/30 | I7: MATH 251,ED2-ME | J7: =#N/A -> #N/A
A8: CHE 153 | B8: ORGANIC CHEMISTRY FOR ENGINEERS | C8: Laryea Michael Konney | D8: ED1-CHE | E8: 120 | F8: VSLA/303/LT/RMA/206 | G8: =E8*1.1 -> 132 | H8: 35/25/20/20/20 | I8: CHE 153,ED1-CHE | J8: 129
A9: CHE 153 | B9: ORGANIC CHEMISTRY FOR ENGINEERS | C9: Laryea Michael Konney | D9: ED1-PCE | E9: 58 | F9: A110/EA | G9: =E9*1.1 -> 63.8 | H9: 30/28 | I9: CHE 153,ED1-PCE | J9: 61
A10: PE 153 | B10: ORGANIC CHEMISTRY FOR ENGINEERS | C10: Laryea Michael Konney | D10: ED1-PE | E10: 130 | F10: VSLA/303/LT/206/RMA | G10: =E10*1.1 -> 143 | H10: 40/26/22/22/20 | I10: PE 153,ED1-PE | J10: 107
A11: CHE 471 | B11: PHARMACEUTICAL TECHNOLOGY | C11: Johnson Raphael | D11: ED4-PCE | E11: 36 | F11: NAF1 | G11: =E11*1.1 -> 39.6 | H11: 36 | I11: =_xlfn.CONCAT(A11,",",D11) -> CHE 471,ED4-PCE | J11: 45
A12: PCE 359 | B12: PETROLEUM FLUID PROPERTIES | C12: Adenutsi Caspar Daniel | D12: ED3-PCE | E12: 51 | F12: A110/EA | G12: =E12*1.1 -> 56.1 | H12: 26/25 | I12: =_xlfn.CONCAT(A12,",",D12) -> PCE 359,ED3-PCE | J12: 99
A13: CENG 291 | B13: ENGINEERING IN SOCIETY | C13: Odame Prince | D13: ED2-BME | E13: 80 | F13: PB214/PB008/PB208 | G13: =E13*1.1 -> 88 | H13: 30/25/25 | I13: CENG 291,ED2-BME
A14: CENG 291 | B14: ENGINEERING IN SOCIETY | C14: Odame Prince | D14: ED2-COE | E14: 255 | F14: PB201/PB008/PB208/PB001/PB020/PB014/PB214 | G14: =E14*1.1 -> 280.5 | H14: 39/30/30/39/39/39/39 | I14: =_xlfn.CONCAT(A14,",",D14) -> CENG 291,ED2-COE | J14: 240
A15: EE 261 | B15: DC MACHINES | C15: Effah Francis Boafo | D15: ED2-EE | E15: 345 | F15: NEB-TF/NEB-SF/NEB-FF1/PB001/PB020/PB014/PB201 | G15: =E15*1.1 -> 379.5 | H15: 72/72/49/38/38/38/38 | I15: EE 261,ED2-EE | J15: 129
D16: Total T1-1 | E16: =SUM(E6:E15) -> 1354 | I16: =_xlfn.CONCAT(A16,",",D16) -> ,Total T1-1 | J16: =#N/A -> #N/A
I17: , | J17: =#N/A -> #N/A
I18: , | J18: =#N/A -> #N/A
A19: Tuesday, 7 April 2026 | I19: Tuesday, 7 April 2026, | J19: =#N/A -> #N/A
A20: Session, 2 (12:00 PM - 2:00 PM) | I20: Session, 2 (12:00 PM - 2:00 PM), | J20: =#N/A -> #N/A
A21: CODE | B21: COURSE NAME | C21: EXAMINER | D21: CLASS | E21: # STDS | F21: ROOM NO. | G21: TO PRT | I21: CODE ,CLASS | J21: =#N/A -> #N/A
A22: COE 363 | B22: =IFERROR(VLOOKUP(I22:I32,Lecturers!A2:F596,6,FALSE),0) -> DATA STRUCTURES AND ALGORITHMS | C22: =VLOOKUP(I22:I32,Lecturers!A2:G598,2,FALSE) -> Adjaidoo Theresa-Samuelle Maame Atwemaah | D22: ED3-COE | E22: =IFERROR(VLOOKUP(I22:I32,Lecturers!A2:F596,3,FALSE),0) -> 270 | F22: COMPUTER BASED | G22: =E22*1.1 -> 297 | I22: COE 363,ED3-COE
A23: CE 255 | B23: THEORY OF STRUCTURES | C23: Ampofo James Wiafe | D23: ED2-CE | E23: 255 | F23: PB001/PB020/PB014/PB201/PB214/PB008/PB208 | G23: =E23*1.1 -> 280.5 | H23: 40/40/40/40/40/28/27 | I23: CE 255,ED2-CE | J23: 285
A24: CE 255 | B24: THEORY OF STRUCTURES | C24: Ampofo James Wiafe | D24: ED2-GEOL | E24: 150 | F24: VSLA/303/LT/206/RMA/RMB | G24: =E24*1.1 -> 165 | H24: 40/30/20/20/20/20 | I24: CE 255,ED2-GEOL | J24: 151
A25: CE 367 | B25: HIGHWAY AND TRANSPORTATION ENGINEERING I | C25: Ababio-Donkor Augustus | D25: ED3-GEOM | E25: 125 | F25: NEB-TF/NEB-FF1 | G25: =E25*1.1 -> 137.5 | H25: 75/50 | I25: =_xlfn.CONCAT(A25,",",D25) -> CE 367,ED3-GEOM | J25: 150
A26: ME 161 | B26: BASIC MECHANICS | C26: Opoku Richard | D26: ED1-CE | E26: 245 | F26: PB001/PB020/PB014/PB201/PB214/PB208/PB008 | G26: =E26*1.1 -> 269.5 | H26: 38/38/38/38/38/28/27 | I26: =_xlfn.CONCAT(A26,",",D26) -> ME 161,ED1-CE | J26: 105
A27: GED 151 | B27: BASIC GEOLOGY | C27: Gawu Simon Kafui Yawo | D27: ED1-GEOL | E27: 125 | F27: A110/EA/VCR/NAF1 | G27: =E27*1.1 -> 137.5 | H27: 30/30/25/40 | I27: =_xlfn.CONCAT(A27,",",D27) -> GED 151,ED1-GEOL | J27: 105
A28: CENG 291 | B28: ENGINEERING IN SOCIETY | C28: Koomson Bennetta | D28: ED2-MSE | E28: 80 | F28: VSLA/303/RMA | G28: =E28*1.1 -> 88 | H28: 35/25/20 | I28: =_xlfn.CONCAT(A28,",",D28) -> CENG 291,ED2-MSE | J28: 148
A29: CENG 291 | B29: ENGINEERING IN SOCIETY | C29: Koomson Bennetta | D29: ED2-METE | E29: 59 | F29: NAF1/A110 | G29: =E29*1.1 -> 64.9 | H29: 35/24 | I29: =_xlfn.CONCAT(A29,",",D29) -> CENG 291,ED2-METE | J29: 148
A30: COE 475P | B30: COMPUTER NETWORKING | C30: Adrah Charles Mawutor | D30: ED4-EE | E30: 215 | F30: NEB-TF/NEB-SF/NEB-FF1/NEB-FF2 | G30: =E30*1.1 -> 236.5 | H30: 70/70/45/30 | I30: =_xlfn.CONCAT(A30,",",D30) -> COE 475P,ED4-EE
A31: ME 499 | B31: OPERATIONS RESEARCH | C31: Mensah Lena Dzifa | D31: ED4-AERO | E31: 2 | F31: NEB-FF2 | G31: =E31*1.1 -> 2.2 | H31: 2 | I31: ME 499,ED4-AERO
A32: IE 351 | B32: OPERATIONS RESEARCH I | C32: Mensah Lena Dzifa | D32: ED3-IND | E32: 72 | F32: NEB-SF | G32: =E32*1.1 -> 79.2 | H32: 72 | I32: =_xlfn.CONCAT(A32,",",D32) -> IE 351,ED3-IND | J32: 143
D33: Total T1-2 | E33: =SUM(E23:E32) -> 1328 | I33: ,Total T1-2 | J33: =#N/A -> #N/A
I34: , | J34: =#N/A -> #N/A
I35: , | J35: =#N/A -> #N/A
A36: Tuesday, 7 April 2026 | I36: Tuesday, 7 April 2026, | J36: =#N/A -> #N/A
A37: Session, 3 (3:00 PM - 5:00 PM) | I37: Session, 3 (3:00 PM - 5:00 PM), | J37: =#N/A -> #N/A
A38: CODE | B38: COURSE NAME | C38: EXAMINER | D38: CLASS | E38: # STDS | F38: ROOM NO. | G38: TO PRT | I38: CODE ,CLASS | J38: =#N/A -> #N/A
A39: CE 477 | B39: =IFERROR(VLOOKUP(I39:I49,Lecturers!A2:F596,6,FALSE),0) -> GEOTECHNICAL ENGINEERING I | C39: =VLOOKUP(I39:I49,Lecturers!A2:G598,2,FALSE) -> Ayeh Felix Jojo Fianko | D39: ED4-CE | E39: =IFERROR(VLOOKUP(I39:I49,Lecturers!A2:F596,3,FALSE),0) -> 35 | F39: VSLA | G39: =E39*1.1 -> 38.5 | H39: 35 | I39: CE 477,ED4-CE
A40: CE 477 | B40: GEOTECHNICAL ENGINEERING I | C40: Ampadu Samuel Innocent Kofi | D40: ED4-GEOL | E40: 95 | F40: NAF1/A110/EA/VCR | G40: =E40*1.1 -> 104.5 | H40: 30/23/22/20 | I40: CE 477,ED4-GEOL | J40: 134
A41: PE 361 | B41: RESERVOIR ENGINEERING II | C41: Adenutsi Caspar Daniel | D41: ED3-PE | E41: 80 | F41: NEB-TF | G41: =E41*1.1 -> 88 | H41: 80 | I41: =_xlfn.CONCAT(A41,",",D41) -> PE 361,ED3-PE | J41: 218
A42: CENG 291 | B42: ENGINEERING IN SOCIETY | C42: Kwao-Boateng Emmanuela | D42: ED2-PCE | E42: 65 | F42: NEB-FF2/NEB-FF1 | G42: =E42*1.1 -> 71.5 | H42: 25/40 | I42: =_xlfn.CONCAT(A42,",",D42) -> CENG 291,ED2-PCE
A43: CENG 291 | B43: ENGINEERING IN SOCIETY | C43: Baah-Ennumh Emmanuel Kwaku | D43: ED2-CHE | E43: 157 | F43: VSLA/303/LT/206/RMA/RMB | G43: =E43*1.1 -> 172.7 | H43: 45/30/22/20/20/20 | I43: =_xlfn.CONCAT(A43,",",D43) -> CENG 291,ED2-CHE | J43: 102
A44: CE 155 | B44: ENVIRONMENTAL STUDIES | C44: Buamah Richard Akwasi | D44: ED1-TEL | E44: 130 | F44: NEB-SF/NEB-TF | G44: =E44*1.1 -> 143 | H44: 65/65 | I44: CE 155,ED1-TEL | J44: 154
A45: CE 155 | B45: ENVIRONMENTAL STUDIES | C45: Appiah-Brempong Miriam | D45: ED1-AERO | E45: 70 | F45: NEB-SF | G45: =E45*1.1 -> 77 | H45: 70 | I45: CE 155,ED1-AERO | J45: 72
A46: CE 155 | B46: ENVIRONMENTAL STUDIES | C46: Essandoh Helen Michelle Korkor | D46: ED1-COE | E46: 262 | F46: PB001/PB020/PB014/PB201/PB214/PB008/PB208/PB212 | G46: =E46*1.1 -> 288.2 | H46: 38/38/38/38/38/26/26/20 | I46: CE 155,ED1-COE | J46: 185
A47: CE 155 | B47: ENVIRONMENTAL STUDIES | C47: Appiah-Brempong Miriam | D47: ED1-IND | E47: 83 | F47: NEB-FF1/NEB-FF2 | G47: =E47*1.1 -> 91.3 | H47: 53/30 | I47: CE 155,ED1-IND | J47: 69
A48: CE 155 | B48: ENVIRONMENTAL STUDIES | C48: Awuah Esi | D48: ED1-ME | E48: 226 | F48: PB001/PB020/PB014/PB201/PB214/PB008/PB208 | G48: =E48*1.1 -> 248.6 | H48: 35/35/35/35/35/26/25 | I48: CE 155,ED1-ME | J48: 166
A49: CE 155 | B49: ENVIRONMENTAL STUDIES | C49: Buamah Richard Akwasi | D49: ED1-AE | E49: 130 | F49: NAF1/A110/EA/VCR | G49: =E49*1.1 -> 143 | H49: 45/30/30/25 | I49: CE 155,ED1-AE | J49: 124
D50: Total T1-3 | E50: =SUM(E39:E49) -> 1333 | I50: ,Total T1-3 | J50: =#N/A -> #N/A
I51: , | J51: =#N/A -> #N/A
I52: , | J52: =#N/A -> #N/A
I53: , | J53: =#N/A -> #N/A
A54: Wednesday, 8 April 2026 | I54: Wednesday, 8 April 2026, | J54: =#N/A -> #N/A
A55: Session, 1 (8:30 AM - 10:30 AM) | I55: Session, 1 (8:30 AM - 10:30 AM), | J55: =#N/A -> #N/A
A56: CODE | B56: COURSE NAME | C56: EXAMINER | D56: CLASS | E56: # STDS | F56: ROOM NO. | G56: TO PRT | I56: CODE ,CLASS | J56: =#N/A -> #N/A
A57: ENGL 263 | B57: =IFERROR(VLOOKUP(I57:I67,Lecturers!A2:F596,6,FALSE),0) -> LITERATURE IN ENGLISH I | C57: =VLOOKUP(I57:I67,Lecturers!A2:G598,2,FALSE) -> Yeboah Philomena Ama Okyeso | D57: ED2-AERO | E57: =IFERROR(VLOOKUP(I57:I67,Lecturers!A2:F596,3,FALSE),0) -> 75 | F57: A110/EA/NAF1 | G57: =E57*1.1 -> 82.5 | H57: 25/25/20 | I57: ENGL 263,ED2-AERO | J57: 178
A58: ENGL 263 | B58: LITERATURE IN ENGLISH I | C58: Yeboah Philomena Ama Okyeso | D58: ED2-AE | E58: 155 | F58: VSLA/303/LT/206/RMA/RMB | G58: =E58*1.1 -> 170.5 | H58: 40/30/22/22/21/20 | I58: =_xlfn.CONCAT(A58,",",D58) -> ENGL 263,ED2-AE | J58: 130
A59: ENGL 263 | B59: LITERATURE IN ENGLISH I | C59: Yeboah Philomena Ama Okyeso | D59: ED2-IND | E59: 80 | F59: NEB-FF1/NEB-FF2 | G59: =E59*1.1 -> 88 | H59: 50/30 | I59: ENGL 263,ED2-IND
A60: ENGL 263 | B60: LITERATURE IN ENGLISH I | C60: Yeboah Philomena Ama Okyeso | D60: ED2-GEOM | E60: 134 | F60: PB001/PB020/PB014/PB208 | G60: =E60*1.1 -> 147.4 | H60: 36/36/36/26 | I60: ENGL 263,ED2-GEOM | J60: 112
A61: AE 373 | B61: MACHINE DESIGN I | C61: Aveyire Joseph | D61: ED3-AE | E61: 100 | F61: PB214/PB008/PB201 | G61: =E61*1.1 -> 110 | H61: 35/30/35 | I61: AE 373,ED3-AE
A62: ME 395 | B62: MECHANICAL ENGINEERING LAB. III | C62: Boahen Samuel | D62: ED3-ME | E62: 225 | F62: PB001/PB020/PB014/PB201/PB214/PB008/PB208 | G62: =E62*1.1 -> 247.5 | H62: 35/35/35/35/35/25/25 | I62: ME 395,ED3-ME | J62: 255
A63: PE 155 | B63: INTRODUCTION TO INFORMATION TECHNOLOGY | C63: Sokama-Neuyam Yen Adams | D63: ED1-PE | E63: 130 | F63: NAF1/A110/EA/VCR | G63: =E63*1.1 -> 143 | H63: 45/30/30/25 | I63: =_xlfn.CONCAT(A63,",",D63) -> PE 155,ED1-PE | J63: 107
A64: TE 451 | B64: FUNDAMENTALS OF NETWORK SECURITY | C64: Agyemang Justice Owusu | D64: ED4-TEL | E64: 140 | F64: NEB-SF | G64: =E64*1.1 -> 154 | H64: 140 | I64: =_xlfn.CONCAT(A64,",",D64) -> TE 451,ED4-TEL | J64: 85
A65: TE 255 | B65: INTRODUCTION TO PROGRAMMING II | C65: Agyemang Justice Owusu | D65: ED2-TEL | E65: 175 | F65: NEB-TF/NEB-SF | G65: =E65*1.1 -> 192.5 | H65: 160/15 | I65: =CONCATENATE(A65,",",D65) -> TE 255,ED2-TEL
A66: MSE 355 | B66: POLYMER PROCESSING | C66: Asare Eric Kwame Anokye | D66: ED3-MSE | E66: 89 | F66: VSLA/LT/206/RMA | G66: =E66*1.1 -> 97.9 | H66: 30/20/20/20 | I66: =_xlfn.CONCAT(A66,",",D66) -> MSE 355,ED3-MSE | J66: 82
A67: BME 461 | B67: BIOMECHANICS I | C67: Odame Prince | D67: ED4-BME | E67: 87 | F67: N1/N2/RMB/303 | G67: =E67*1.1 -> 95.7 | H67: 25/20/20/22 | I67: BME 461,ED4-BME
D68: Total W1-1 | E68: =SUM(E58:E67) -> 1315 | I68: =_xlfn.CONCAT(A68,",",D68) -> ,Total W1-1 | J68: =#N/A -> #N/A
I69: =_xlfn.CONCAT(A69,",",D69) -> , | J69: =#N/A -> #N/A
I70: , | J70: =#N/A -> #N/A
A71: Wednesday, 8 April 2026 | I71: Wednesday, 8 April 2026, | J71: =#N/A -> #N/A
A72: Session, 2 (12:00 PM - 2:00 PM) | I72: Session, 2 (12:00 PM - 2:00 PM), | J72: =#N/A -> #N/A
A73: CODE | B73: COURSE NAME | C73: EXAMINER | D73: CLASS | E73: # STDS | F73: ROOM NO. | G73: TO PRT | I73: CODE ,CLASS | J73: =#N/A -> #N/A
A74: COE 453 | B74: =IFERROR(VLOOKUP(I74:I86,Lecturers!A2:F596,6,FALSE),0) -> DISTRIBUTED COMPUTING | C74: =VLOOKUP(I74:I86,Lecturers!A2:G598,2,FALSE) -> Keelson Eliel | D74: ED4-COE | E74: =IFERROR(VLOOKUP(I74:I86,Lecturers!A2:F596,3,FALSE),0) -> 140 | F74: NEB-TF/NEB-SF | G74: =E74*1.1 -> 154 | H74: 80/60 | I74: =_xlfn.CONCAT(A74,",",D74) -> COE 453,ED4-COE | J74: 136
A75: CHE 353 | B75: CHEMICAL ENGINEERING LABORATORY I | C75: Mensah Mary | D75: ED3-CHE | E75: 100 | F75: LT/206/RMB/RMA/303 | G75: =E75*1.1 -> 110 | H75: 20/20/20/20/20 | I75: =_xlfn.CONCAT(A75,",",D75) -> CHE 353,ED3-CHE | J75: 65
A76: PCE 353 | B76: PETROCHEMICAL ENGINEERING LABORATORY I | C76: Mensah Mary | D76: ED3-PCE | E76: 51 | F76: EA/A110 | G76: =E76*1.1 -> 56.1 | H76: 26/25 | I76: PCE 353,ED3-PCE | J76: =#N/A -> #N/A
A77: TE 357 | B77: OPTICAL COMMUNICATION | C77: Gadze James Dzisi | D77: ED3-TEL | E77: 140 | F77: NEB-SF/NEB-FF1/NEB-FF2 | G77: =E77*1.1 -> 154 | H77: 70/45/25 | I77: =CONCATENATE(A77,",",D77) -> TE 357,ED3-TEL
A78: PE 253 | B78: BASIC GEOLOGY | C78: Quaye Jonathan Atuquaye | D78: ED2-PE | E78: 95 | F78: NAF1/A110/EA/VCR | G78: =E78*1.1 -> 104.5 | H78: 30/23/22/20 | I78: =_xlfn.CONCAT(A78,",",D78) -> PE 253,ED2-PE | J78: 184
A79: ME 473 | B79: COMPUTER AIDED DESIGN AND MANUFACTURING | C79: Afriyie Nyarko Frank Kwabena | D79: ED4-ME | E79: 35 | F79: VSLA | G79: =E79*1.1 -> 38.5 | H79: 35 | I79: ME 473,ED4-ME | J79: 87
A80: ME 473 | B80: COMPUTER AIDED DESIGN AND MANUFACTURING | C80: Afriyie Nyarko Frank Kwabena | D80: ED4-AERO | E80: 7 | F80: VCR | G80: =E80*1.1 -> 7.7 | H80: 7 | I80: ME 473,ED4-AERO | J80: 87
A81: IE 457 | B81: ADVANCED MANUFACTURING TECHNOLOGY II | C81: Takyi Gabriel | D81: ED4-IND | E81: 67 | F81: NEB-FF1/NEB-FF2 | G81: =E81*1.1 -> 73.7 | H81: 42/25 | I81: =_xlfn.CONCAT(A81,",",D81) -> IE 457,ED4-IND | J81: 33
A82: EE 371 | B82: LINEAR ELECTRONIC CIRCUITS | C82: Sekyere Yaw Opoku Mensah | D82: ED3-EE | E82: 240 | F82: PB001/PB020/PB014/PB201/PB214/PB008/PB208 | G82: =E82*1.1 -> 264 | H82: 38/38/38/38/38/25/25 | I82: EE 371,ED3-EE | J82: 183
A83: PCE 253 | B83: INTRODUCTION TO PETROCHEMICAL INDUSTRIES | C83: Baidoo Martina Francisca | D83: ED2-PCE | E83: 65 | F83: NEB-TF | G83: =E83*1.1 -> 71.5 | H83: 65 | I83: PCE 253,ED2-PCE | J83: 128
A84: MME 365 | B84: ENGINEERING THERMODYNAMICS | C84: Amoabeng Kofi Owura | D84: ED3-MARI | E84: 40 | F84: NAF1 | G84: =E84*1.1 -> 44 | H84: 40 | I84: MME 365,ED3-MARI | J84: 66
A85: CHEM 151 | B85: GENERAL CHEMISTRY | C85: Sarpong Lilian | D85: ED1-BME | E85: 136 | F85: VSLA/303/LT/206/RMA/RMB | G85: =E85*1.1 -> 149.6 | H85: 40/30/22/22/22 | I85: =CONCATENATE(A85,",",D85) -> CHEM 151,ED1-BME
A86: ME 295 | B86: MECHANICAL ENGINEERING LAB. I | C86: Quansah David Ato | D86: ED2-ME | E86: 242 | F86: PB001/PB020/PB014/PB201/PB214/PB208/PB008 | G86: =E86*1.1 -> 266.2 | H86: 38/38/38/38/38/26/26 | I86: ME 295,ED2-ME | J86: =#N/A -> #N/A
D87: Total W1-2 | E87: =SUM(E74:E86) -> 1358 | I87: ,Total W1-2 | J87: =#N/A -> #N/A
I88: , | J88: =#N/A -> #N/A
I89: , | J89: =#N/A -> #N/A
A90: Wednesday, 8 April 2026 | I90: Wednesday, 8 April 2026, | J90: =#N/A -> #N/A
A91: Session, 3 (3:00 PM - 5:00 PM) | I91: Session, 3 (3:00 PM - 5:00 PM), | J91: =#N/A -> #N/A
A92: CODE | B92: COURSE NAME | C92: EXAMINER | D92: CLASS | E92: # STDS | F92: ROOM NO. | G92: TO PRT | I92: CODE ,CLASS | J92: =#N/A -> #N/A
A93: CE 471 | B93: =IFERROR(VLOOKUP(I93:I107,Lecturers!A2:F596,6,FALSE),0) -> IRRIGATION AND DRAINAGE ENGINEERING | C93: =VLOOKUP(I93:I107,Lecturers!A2:G598,2,FALSE) -> Anornu Geophrey Kwame | D93: ED4-CE | E93: =IFERROR(VLOOKUP(I93:I107,Lecturers!A2:F596,3,FALSE),0) -> 180 | F93: NEB-TF/NEB-SF/NEB-FF1 | G93: =E93*1.1 -> 198 | H93: 65/65/50 | I93: =_xlfn.CONCAT(A93,",",D93) -> CE 471,ED4-CE | J93: 170
A94: AE 457 | B94: CROP PROCESSING | C94: Darko Joseph Ofei | D94: ED4-AE | E94: 103 | F94: NAF1/A110/EA | G94: =E94*1.1 -> 113.3 | H94: 45/30/27 | I94: AE 457,ED4-AE | J94: 83
A95: IE 355 | B95: DISCRETE EVENT SIMULATION | C95: Takyi Gabriel | D95: ED3-IND | E95: 72 | F95: NEB-TF | G95: =E95*1.1 -> 79.2 | H95: 72 | I95: =_xlfn.CONCAT(A95,",",D95) -> IE 355,ED3-IND
A96: GED 267 | B96: COMPUTER PROGRAMMING | C96: Kwaw Albert Kwame | D96: ED2-GEOL | E96: 150 | F96: VSLA/303/LT/206/RMA/RMB | G96: =E96*1.1 -> 165 | H96: 40/26/22/22/20/20 | I96: GED 267,ED2-GEOL | J96: 151
A97: ME 159 | B97: TECHNICAL DRAWING | C97: Sunnu Albert Kojo | D97: ED1-MARI | E97: 46 | F97: NEB-FF1 | G97: =E97*1.1 -> 50.6 | H97: 46 | I97: =_xlfn.CONCAT(A97,",",D97) -> ME 159,ED1-MARI
A98: ME 159 | B98: TECHNICAL DRAWING | C98: Sunnu Albert Kojo | D98: ED1-ME | E98: 226 | F98: PB020/PB014/PB201/PB214/PB008/PB208/PB001 | G98: =E98*1.1 -> 248.6 | H98: 35/35/35/35/27/27/32 | I98: ME 159,ED1-ME | J98: 166
A99: ME 159 | B99: TECHNICAL DRAWING | C99: Sunnu Albert Kojo | D99: ED1-TEL | E99: 130 | F99: PB020/PB014/PB201/PB008 | G99: =E99*1.1 -> 143 | H99: 35/35/35/25 | I99: ME 159,ED1-TEL | J99: 107
A100: AME 485 | B100: AUTOMATIC POWER TRAIN | C100: Abu Frimpong Solomon | D100: ED4-AUTO | E100: 32 | F100: NAF1 | G100: =E100*1.1 -> 35.2 | H100: 32 | I100: =_xlfn.CONCAT(A100,",",D100) -> AME 485,ED4-AUTO | J100: 39
...

Sheet Lecturers
A1: Unnamed: 0 | B1: Unnamed: 6 | C1: No of students | E1: BSC. AEROSPACE ENG., Year 1 | F1: Unnamed: 4
A2: =_xlfn.CONCAT(E2,",",D2) -> AERO 157,ED1-AERO | B2: Oppong David Kofi | C2: 70 | D2: ED1-AERO | E2: AERO 157 | F2: INTRODUCTION TO AVIATION TECHNOLOGY
A3: CE 155,ED1-AERO | B3: Appiah-Brempong Miriam | C3: 70 | D3: =D2 -> ED1-AERO | E3: CE 155 | F3: ENVIRONMENTAL STUDIES
A4: EE 151,ED1-AERO | B4: Oteng Gyasi Kwame | C4: 70 | D4: =D3 -> ED1-AERO | E4: EE 151 | F4: APPLIED ELECTRICITY
A5: ENGL 157,ED1-AERO | B5: Appiah Franklin Benjamin | C5: 70 | D5: =D4 -> ED1-AERO | E5: ENGL 157 | F5: COMMUNICATION SKILLS I
A6: MATH 151,ED1-AERO | B6: Fosu Gabriel Obed | C6: 70 | D6: =D5 -> ED1-AERO | E6: MATH 151 | F6: ALGEBRA
A7: ME 157,ED1-AERO | B7: Sackey Michael Nii | C7: 70 | D7: =D6 -> ED1-AERO | E7: ME 157 | F7: INTRODUCTION TO INFORMATION TECHNOLOGY
A8: ME 159,ED1-AERO | B8: Oppong Tawiah Peter | C8: 70 | D8: =D7 -> ED1-AERO | E8: ME 159 | F8: TECHNICAL DRAWING
A9: ME 281,ED2-AERO | B9: Amoabeng Kofi Owura | C9: 75 | D9: ED2-AERO | E9: ME 281 | F9: ENGINEERING MATERIALS I
A10: CENG 291,ED2-AERO | B10: Oppong David Kofi | C10: 75 | D10: =D9 -> ED2-AERO | E10: CENG 291 | F10: ENGINEERING IN SOCIETY
A11: AERO 293,ED2-AERO | B11: Oppong David Kofi | C11: 75 | D11: =D10 -> ED2-AERO | E11: AERO 293 | F11: AEROSPACE ENGINEERING VACATION TRAINING I
A12: ME 255,ED2-AERO | B12: Agyei Agyemang Anthony | C12: 75 | D12: =D11 -> ED2-AERO | E12: ME 255 | F12: STRENGTH OF MATERIALS I
A13: ENGL 263,ED2-AERO | B13: Yeboah Philomena Ama Okyeso | C13: 75 | D13: =D12 -> ED2-AERO | E13: ENGL 263 | F13: LITERATURE IN ENGLISH I
A14: MATH 251,ED2-AERO | B14: Wireko Fredrick Asenso | C14: 75 | D14: =D13 -> ED2-AERO | E14: MATH 251 | F14: DIFFERENTIAL EQUATIONS
A15: ME 251,ED2-AERO | B15: Fiagbe Yesuenyeagbe Atsu Kwabla | C15: 75 | D15: =D14 -> ED2-AERO | E15: ME 251 | F15: INTRODUCTION TO FLUID MECHANICS
A16: ME 261,ED2-AERO | B16: Ampofo Joshua | C16: 75 | D16: =D15 -> ED2-AERO | E16: ME 261 | F16: ENGINEERING MECHANICS II:DYNAMICS
A17: ME 295,ED2-AERO | B17: David Kofi Oppong | C17: 75 | D17: =D16 -> ED2-AERO | E17: ME 295 | F17: MECHANICAL ENGINEERING LAB. I
A18: ECON 151,ED3-AERO | B18: Takyi Paul Owusu | C18: 76 | D18: ED3-AERO | E18: ECON 151 | F18: INTRODUCTION TO ECONOMICS I
A19: AERO 393,ED3-AERO | B19: Oppong David Kofi | C19: 76 | D19: =D18 -> ED3-AERO | E19: AERO 393 | F19: AEROSPACE ENGINEERING VACATION TRAINING II
A20: AERO 351,ED3-AERO | B20: Bofah Kwasi Kete | C20: 76 | D20: =D19 -> ED3-AERO | E20: AERO 351 | F20: AERODYNAMICS I
A21: AERO 391,ED3-AERO | B21: Kwasi Kete Bofah | C21: 76 | D21: =D20 -> ED3-AERO | E21: AERO 391 | F21: AEROSPACE INDUSTRY AND ENGINEERING
A22: AERO 395,ED3-AERO | B22: Oppong David Kofi | C22: 76 | D22: =D21 -> ED3-AERO | E22: AERO 395 | F22: AEROSPACE ENGINEERING LAB. I
A23: MATH 351,ED3-AERO | B23: Borkor Reindorf Nartey | C23: 76 | D23: =D22 -> ED3-AERO | E23: MATH 351 | F23: NUMERICAL ANALYSIS
A24: STAT 253,ED3-AERO | B24: Carole Fredua Amoako-Yirenkyi | C24: 76 | D24: =D23 -> ED3-AERO | E24: STAT 253 | F24: PROBABILITY AND STATISTICS
A25: ME 363,ED3-AERO | B25: Faisal Wahib Adam | C25: 76 | D25: =D24 -> ED3-AERO | E25: ME 363 | F25: AUTOMATIC CONTROL I
A26: AERO 473,ED4-AERO | B26: Oppong David Kofi | C26: 61 | D26: ED4-AERO | E26: AERO 473 | F26: AEROSPACE VEHICLE DESIGN
A27: AERO 483,ED4-AERO | B27: Oppong David Kofi | C27: 61 | D27: =D26 -> ED4-AERO | E27: AERO 483 | F27: AVIONICS
A28: AERO 491,ED4-AERO | B28: Takyi Gabriel | C28: 61 | D28: =D27 -> ED4-AERO | E28: AERO 491 | F28: AVIATION BUSINESS MANAGEMENT
A29: AERO 493,ED4-AERO | B29: Oppong David Kofi | C29: 61 | D29: =D28 -> ED4-AERO | E29: AERO 493 | F29: AEROSPACE ENGINEERING VACATION TRAINING III
A30: AERO 495,ED4-AERO | B30: Oppong Tawiah Peter | C30: 61 | D30: =D29 -> ED4-AERO | E30: AERO 495 | F30: AIRCRAFT MAINTENANCE ENGINEERING
A31: AERO 497,ED4-AERO | B31: Tay Godwin Fabiola Kwaku | C31: 61 | D31: =D30 -> ED4-AERO | E31: AERO 497 | F31: PROJECT I
A32: ME 451,ED4-AERO | B32: Opoku Richard | C32: 53 | D32: =D31 -> ED4-AERO | E32: ME 451 | F32: BEHAVIOUR OF REAL FLUIDS
A33: ME 473,ED4-AERO | B33: Afriyie Nyarko Frank Kwabena | C33: 7 | D33: =D32 -> ED4-AERO | E33: ME 473 | F33: COMPUTER AIDED DESIGN AND MANUFACTURING
A34: ME 499,ED4-AERO | B34: Mensah Lena Dzifa | C34: 2 | D34: =D33 -> ED4-AERO | E34: ME 499 | F34: OPERATIONS RESEARCH
A36: AE 153,ED1-AE | B36: Bessah Enoch | C36: 128 | D36: ED1-AE | E36: AE 153 | F36: AGRIC. METEOROLOGY AND CLIMATOLOGY
A37: EE 151,ED1-AE | B37: Prah II Nicholas Kwesi | C37: 135 | D37: =D36 -> ED1-AE | E37: EE 151 | F37: APPLIED ELECTRICITY
A38: ENGL 157,ED1-AE | B38: Yeboah Philomena Ama Okyeso | C38: 128 | D38: =D37 -> ED1-AE | E38: ENGL 157 | F38: COMMUNICATION SKILLS I
A39: MATH 151,ED1-AE | B39: Asamoah Joshua Kiddy Kwasi | C39: 128 | D39: =D38 -> ED1-AE | E39: MATH 151 | F39: ALGEBRA
A40: ME 159,ED1-AE | B40: Aveyire Joseph | C40: 128 | D40: =D39 -> ED1-AE | E40: ME 159 | F40: TECHNICAL DRAWING
A41: ME 195,ED1-AE | B41: Oppong David Kofi | C41: 128 | D41: =D40 -> ED1-AE | E41: ME 195 | F41: ENGINEERING TECHNOLOGY I
A42: CE 155,ED1-AE | B42: Buamah Richard Akwasi | C42: 130 | D42: =D41 -> ED1-AE | E42: CE 155 | F42: ENVIRONMENTAL STUDIES
A43: CENG 291,ED2-AE | B43: Lavie Jerome Dela | C43: 155 | D43: ED2-AE | E43: CENG 291 | F43: ENGINEERING IN SOCIETY
A44: ENGL 263,ED2-AE | B44: Yeboah Philomena Ama Okyeso | C44: 155 | D44: =D43 -> ED2-AE | E44: ENGL 263 | F44: LITERATURE IN ENGLISH I
A45: MATH 251,ED2-AE | B45: Wireko Fredrick Asenso | C45: 155 | D45: =D44 -> ED2-AE | E45: MATH 251 | F45: DIFFERENTIAL EQUATIONS
A46: ME 251,ED2-AE | B46: Fiagbe Yesuenyeagbe Atsu Kwabla | C46: 155 | D46: =D45 -> ED2-AE | E46: ME 251 | F46: FLUID MECHANICS I
A47: ME 255,ED2-AE | B47: Boahen Samuel | C47: 165 | D47: =D46 -> ED2-AE | E47: ME 255 | F47: STRENGTH OF MATERIALS I
A48: ME 259,ED2-AE | B48: Asante Eric Amoah | C48: 155 | D48: =D47 -> ED2-AE | E48: ME 259 | F48: APPLICATIONS OF COMPUTER GRAPHICS
A49: ME 265,ED2-AE | B49: Forson Francis Kofi | C49: 155 | D49: =D48 -> ED2-AE | E49: ME 265 | F49: THERMODYNAMICS I
A50: ME 295,ED2-AE | B50: Adam Faisal Wahib | C50: 155 | D50: =D49 -> ED2-AE | E50: ME 295 | F50: MECHANICAL ENGINEERING LAB. I
A51: AE 351,ED3-AE | B51: Kyei-Baffour Nicholas | C51: 100 | D51: ED3-AE | E51: AE 351 | F51: SOIL AND WATER ENGINEERING
A52: AE 353,ED3-AE | B52: Akowuah Joseph Oppong | C52: 100 | D52: =D51 -> ED3-AE | E52: AE 353 | F52: AGRICULTURAL MATERIALS HANDLING AND PROCESSING
A53: AE 373,ED3-AE | B53: Aveyire Joseph | C53: 100 | D53: =D52 -> ED3-AE | E53: AE 373 | F53: MACHINE DESIGN I
A54: AE 381,ED3-AE | B54: Amponsah William | C54: 100 | D54: =D53 -> ED3-AE | E54: AE 381 | F54: COMPUTER APPLICATION FOR AGRICULTURAL ENGINEERS
A55: MATH 351,ED3-AE | B55: Borkor Reindorf Nartey | C55: 100 | D55: =D54 -> ED3-AE | E55: MATH 351 | F55: NUMERICAL ANALYSIS
A56: ME 355,ED3-AE | B56: Agyei Agyemang Anthony | C56: 100 | D56: =D55 -> ED3-AE | E56: ME 355 | F56: STRENGTH OF MATERIALS II
A57: ME 365,ED3-AE | B57: Forson Francis Kofi | C57: 100 | D57: =D56 -> ED3-AE | E57: ME 365 | F57: THERMODYNAMICS II
A58: AE 451,ED4-AE | B58: Agodzo Sampson Kwaku | C58: 103 | D58: ED4-AE | E58: AE 451 | F58: IRRIGATION AND DRAINAGE
A59: AE 453,ED4-AE | B59: Lavie Jerome Dela | C59: 103 | D59: =D58 -> ED4-AE | E59: AE 453 | F59: ENVIRONMENTAL CONTROL AND LIVESTOCK HOUSING
A60: AE 457,ED4-AE | B60: Darko Joseph Ofei | C60: 103 | D60: =D59 -> ED4-AE | E60: AE 457 | F60: CROP PROCESSING
A61: AE 459,ED4-AE | B61: Aikins Stephen Hill Mends | C61: 103 | D61: =D60 -> ED4-AE | E61: AE 459 | F61: ADVANCED FARM POWER AND MACHINERY
A62: AE 471,ED4-AE | B62: Bart Plange Ato | C62: 103 | D62: =D61 -> ED4-AE | E62: AE 471 | F62: FARM STRUCTURES
A63: AE 497,ED4-AE | B63: Darko Clara Bernice | C63: 103 | D63: =D62 -> ED4-AE | E63: AE 497 | F63: PROJECT I
A64: ME 491,ED4-AE | B64: Aikins Stephen Hill Mends | C64: 103 | D64: =D63 -> ED4-AE | E64: ME 491 | F64: ENGINEERING ECONOMICS AND MANAGEMENT
A65: =_xlfn.CONCAT(E65,",",D65) -> AE 499,ED4-AE | B65: Asante Eric Amoah | C65: 103 | D65: =D64 -> ED4-AE | E65: AE 499 | F65: VACATION TRAINING
A66: AI 150,ED1-AUTO | B66: Nunoo-Mensah Henry | C66: 85 | D66: ED1-AUTO | E66: AI 150 | F66: FUNDAMENTALS OF RESPONSIBLE AI FOR ALL
A67: AME 167,ED1-AUTO | B67: Tay Godwin Fabiola Kwaku | C67: 85 | D67: =D66 -> ED1-AUTO | E67: AME 167 | F67: COMPUTER PROGRAMMING FOR ENGINEERS
A68: ECON 151,ED1-AUTO | B68: Takyi Paul Owusu | C68: 85 | D68: =D67 -> ED1-AUTO | E68: ECON 151 | F68: INTRODUCTION TO ECONOMICS
A69: EE 151,ED1-AUTO | B69: Acheampong Francisca Adoma | C69: 87 | D69: =D68 -> ED1-AUTO | E69: EE 151 | F69: APPLIED ELECTRICITY
A70: ENGL 157,ED1-AUTO | B70: Sarfo-Adu Kwasi | C70: 85 | D70: =D69 -> ED1-AUTO | E70: ENGL 157 | F70: COMMUNICATION SKILLS I
A71: MATH 151,ED1-AUTO | B71: Azure Isaac | C71: 85 | D71: =D70 -> ED1-AUTO | E71: MATH 151 | F71: ALGEBRA
A72: ME 159,ED1-AUTO | B72: Sekyere Charles Kofi Kafui | C72: 85 | D72: =D71 -> ED1-AUTO | E72: ME 159 | F72: TECHNICAL DRAWING
A73: ME 195,ED1-AUTO | B73: Ampofo Joshua | C73: 85 | D73: =D72 -> ED1-AUTO | E73: ME 195 | F73: ENGINEERING TECHNOLOGY
A74: AME 295,ED2-AUTO | B74: Ayetor Godwin Kafui Kwesi | C74: 82 | D74: ED2-AUTO | E74: AME 295 | F74: AUTOMOBILE ENGINEERING LABORATORY I
A75: CENG 291,ED2-AUTO | B75: Amoabeng Kofi Owura | C75: 82 | D75: =D74 -> ED2-AUTO | E75: CENG 291 | F75: ENGINEERING IN SOCIETY
A76: MATH 251,ED2-AUTO | B76: Eghan Rhydal Esi | C76: 82 | D76: =D75 -> ED2-AUTO | E76: MATH 251 | F76: DIFFERENTIAL EQUATIONS
A77: ME 251,ED2-AUTO | B77: Tay Godwin Fabiola Kwaku | C77: 82 | D77: =D76 -> ED2-AUTO | E77: ME 251 | F77: INTRODUCTION TO FLUID MECHANICS
A78: ME 255,ED2-AUTO | B78: Dzebre Denis Edem Kwame | C78: 85 | D78: =D77 -> ED2-AUTO | E78: ME 255 | F78: STRENGTH OF MATERIALS I
A79: ME 259,ED2-AUTO | B79: Ayetor Godwin Kafui Kwesi | C79: 82 | D79: =D78 -> ED2-AUTO | E79: ME 259 | F79: APPLICATIONS OF COMPUTER GRAPHICS
A80: ME 261,ED2-AUTO | B80: Ampofo Joshua | C80: 82 | D80: =D79 -> ED2-AUTO | E80: ME 261 | F80: ENGINEERING MECHANICS II:DYNAMICS
A81: ME 281,ED2-AUTO | B81: Boahen Samuel | C81: 82 | D81: =D80 -> ED2-AUTO | E81: ME 281 | F81: ENGINEERING MATERIALS I
A83: AME 365,ED3-AUTO | B83: Forson Francis Kofi | C83: 40 | D83: ED3-AUTO | E83: AME 365 | F83: HEAT TRANSFER AND COMBUSTION
A84: AME 371,ED3-AUTO | B84: Ayetor Godwin Kafui Kwesi | C84: 40 | D84: =D83 -> ED3-AUTO | E84: AME 371 | F84: LAND VEHICLE DESIGN
A85: AME 373,ED3-AUTO | B85: Andoh Prince Yaw | C85: 40 | D85: =D84 -> ED3-AUTO | E85: AME 373 | F85: DESIGN OF AUTO MECHANICAL SYSTEMS
A86: AME 379,ED3-AUTO | B86: Ayetor Godwin Kafui Kwesi | C86: 40 | D86: =D85 -> ED3-AUTO | E86: AME 379 | F86: AUTOMOBILE ENGINEERING VACATION TRAINING I
A87: AME 381,ED3-AUTO | B87: Ayetor Godwin Kafui Kwesi | C87: 40 | D87: =D86 -> ED3-AUTO | E87: AME 381 | F87: AUTOMOTIVE WORKSHOP PRACTICE I
A88: AME 395,ED3-AUTO | B88: Dzebre Denis Edem Kwame | C88: 40 | D88: =D87 -> ED3-AUTO | E88: AME 395 | F88: AUTOMOBILE ENGINEERING LABORATORY III
A89: MATH 351,ED3-AUTO | B89: Azure Isaac | C89: 40 | D89: =D88 -> ED3-AUTO | E89: MATH 351 | F89: NUMERICAL ANALYSIS
A90: ME 361,ED3-AUTO | B90: Ampofo Joshua | C90: 40 | D90: =D89 -> ED3-AUTO | E90: ME 361 | F90: DYNAMICS OF MACHINERY
A91: STAT 253,ED3-AUTO | B91: Okutu John Kwadey | C91: 40 | D91: =D90 -> ED3-AUTO | E91: STAT 253 | F91: PROBABILITY AND STATISTICS
A92: AME 455,ED4-AUTO | B92: Sekyere Charles Kofi Kafui | C92: 32 | D92: ED4-AUTO | E92: AME 455 | F92: VEHICLE AIR-CONDITIONING AND REFRIGERATION
A93: AME 467,ED4-AUTO | B93: Abu Frimpong Solomon | C93: 32 | D93: =D92 -> ED4-AUTO | E93: AME 467 | F93: AUTOMOTIVE COMPRESSION-IGNITION ENGINES
A94: AME 479,ED4-AUTO | B94: Afriyie Nyarko Frank Kwabena | C94: 32 | D94: =D93 -> ED4-AUTO | E94: AME 479 | F94: AUTOMOBILE ENGINEERING VACATION TRAINING II
A95: AME 485,ED4-AUTO | B95: Abu Frimpong Solomon | C95: 32 | D95: =D94 -> ED4-AUTO | E95: AME 485 | F95: AUTOMATIC POWER TRAIN
A96: AME 495,ED4-AUTO | B96: Ayetor Godwin Kafui Kwesi | C96: 32 | D96: =D95 -> ED4-AUTO | E96: AME 495 | F96: AUTOMOTIVE WORKSHOP PRACTICE II
A97: AME 497,ED4-AUTO | B97: Tay Godwin Fabiola Kwaku | C97: 32 | D97: =D96 -> ED4-AUTO | E97: AME 497 | F97: FINAL YEAR PROJECT I
A98: ME 453,ED4-AUTO | B98: Fiagbe Yesuenyeagbe Atsu Kwabla | C98: 32 | D98: =D97 -> ED4-AUTO | E98: ME 453 | F98: HYDRAULICS AND PNEUMATICS
A99: ME 491,ED4-AUTO | B99: Asiedu Charlotte | C99: 32 | D99: =D98 -> ED4-AUTO | E99: ME 491 | F99: ENGINEERING ECONOMY AND MANAGEMENT
A100: BME 161,ED1-BME | B100: Adjei Prince Ebenezer | C100: 136 | D100: ED1-BME | E100: BME 161 | F100: CELL BIOLOGY
A101: CHEM 151,ED1-BME | B101: Sarpong Lilian | C101: 136 | D101: ED1-BME | E101: CHEM 151 | F101: GENERAL CHEMISTRY
A102: COE 153,ED1-BME | B102: Addo Daniel Akwei | C102: 136 | D102: =D101 -> ED1-BME | E102: COE 153 | F102: ENGINEERING TECHNOLOGY
...

Sheet TALLY
B1: T1 | E1: W1 | H1: H1 | K1: F1 | N1: M2 | Q1: T2 | T1: W2 | W1: H2 | Z1: F2 | AC1: M3 | AF1: T3 | AI1: W3 | AL1: H3 | AO1: F3
B2: S1 | C2: S2 | D2: S3 | E2: S1 | F2: S2 | G2: S3 | H2: S1 | I2: S2 | J2: S3 | K2: S1 | L2: S2 | M2: S3 | N2: S1 | O2: S2 | P2: S3 | Q2: S1 | R2: S2 | S2: S3 | T2: S1 | U2: S2 | V2: S3 | W2: S1 | X2: S2 | Y2: S3 | Z2: S1 | AA2: S2 | AB2: S3 | AC2: S1 | AD2: S2 | AE2: S3 | AF2: S1 | AG2: S2 | AH2: S3 | AI2: S1 | AJ2: S2 | AK2: S3 | AL2: S1 | AM2: S2 | AN2: S3 | AO2: S1 | AP2: S2 | AQ2: S3 | AS2: T1 | AT2: W1 | AU2: H1 | AV2: F1 | AW2: M2 | AX2: T2 | AY2: W2 | AZ2: H2 | BA2: F2 | BB2: M3 | BC2: T3 | BD2: W3 | BE2: H3 | BF2: F3
A3: ED1-AE | B3: =COUNTIF(TT!$D$6:$D$15,TALLY!A3) -> 0 | C3: =COUNTIF(TT!$D$22:$D$32,TALLY!A3) -> 0 | D3: =COUNTIF(TT!$D$39:$D$49,TALLY!A3) -> 1 | E3: =COUNTIF(TT!$D$57:$D$67,TALLY!A3) -> 0 | F3: =COUNTIF(TT!$D$74:$D$86,TALLY!A3) -> 0 | G3: =COUNTIF(TT!$D$93:$D$107,TALLY!A3) -> 0 | H3: =COUNTIF(TT!$D$113:$D$129,TALLY!A3) -> 0 | I3: =COUNTIF(TT!$D$135:$D$155,TALLY!A3) -> 0 | J3: =COUNTIF(TT!$D$162:$D$173,TALLY!A3) -> 0 | K3: =COUNTIF(TT!$D$180:$D$199,TALLY!A3) -> 1 | L3: =COUNTIF(TT!$D$207:$D$215,TALLY!A3) -> 0 | M3: =COUNTIF(TT!$D$224:$D$231,TALLY!A3) -> 0 | N3: =COUNTIF(TT!$D$237:$D$249,TALLY!A3) -> 1 | O3: =COUNTIF(TT!$D$256:$D$264,TALLY!A3) -> 0 | P3: =COUNTIF(TT!$D$271:$D$286,TALLY!A3) -> 0 | Q3: =COUNTIF(TT!$D$293:$D$300,TALLY!A3) -> 0 | R3: =COUNTIF(TT!$D$307:$D$319,TALLY!A3) -> 1 | S3: =COUNTIF(TT!$D$326:$D$334,TALLY!A3) -> 0 | T3: =COUNTIF(TT!$D$341:$D$350,TALLY!A3) -> 0 | U3: =COUNTIF(TT!$D$357:$D$366,TALLY!A3) -> 0 | V3: =COUNTIF(TT!$D$373:$D$383,TALLY!A3) -> 0 | W3: =COUNTIF(TT!$D$390:$D$405,TALLY!A3) -> 1 | X3: =COUNTIF(TT!$D$412:$D$423,TALLY!A3) -> 0 | Y3: =COUNTIF(TT!$D$430:$D$438,TALLY!A3) -> 0 | Z3: =COUNTIF(TT!$D$443:$D$457,TALLY!A3) -> 0 | AA3: =COUNTIF(TT!$D$464:$D$474,TALLY!A3) -> 0 | AB3: =COUNTIF(TT!$D$481:$D$494,TALLY!A3) -> 0 | AC3: =COUNTIF(TT!$D$503:$D$522,TALLY!A3) -> 0 | AD3: =COUNTIF(TT!$D$529:$D$541,TALLY!A3) -> 0 | AE3: =COUNTIF(TT!$D$548:$D$561,TALLY!A3) -> 1 | AF3: =COUNTIF(TT!$D$574:$D$584,TALLY!A3) -> 0 | AG3: =COUNTIF(TT!$D$591:$D$601,TALLY!A3) -> 0 | AH3: =COUNTIF(TT!$D$608:$D$619,TALLY!A3) -> 0 | AI3: =COUNTIF(TT!$D$628:$D$647,TALLY!A3) -> 1 | AJ3: =COUNTIF(TT!$D$654:$D$668,TALLY!A3) -> 0 | AK3: =COUNTIF(TT!$D$675:$D$685,TALLY!A3) -> 0 | AL3: =COUNTIF(TT!$D$692:$D$702,TALLY!A3) -> 0 | AM3: =COUNTIF(TT!$D$709:$D$721,TALLY!A3) -> 0 | AN3: =COUNTIF(TT!$D$728:$D$737,TALLY!A3) -> 0 | AO3: =COUNTIF(TT!$D$744:$D$753,TALLY!A3) -> 0 | AP3: =COUNTIF(TT!$D$759:$D$774,TALLY!A3) -> 0 | AQ3: =COUNTIF(TT!$D$781:$D$789,TALLY!A3) -> 0 | AR3: ED1-AE | AS3: =SUM($B3:$D3) -> 1 | AT3: =SUM(E3:G3) -> 0 | AU3: =SUM(H3:J3) -> 0 | AV3: =SUM(K3:M3) -> 1 | AW3: =SUM(N3:P3) -> 1 | AX3: =SUM($Q3:$S3) -> 1 | AY3: =SUM(T3:V3) -> 0 | AZ3: =SUM(W3:Y3) -> 1 | BA3: =SUM(Z3:AB3) -> 0 | BB3: =SUM(AC3:AE3) -> 1 | BC3: =SUM(AF3:AH3) -> 0 | BD3: =SUM(AI3:AK3) -> 1 | BE3: =SUM(AL3:AN3) -> 0 | BF3: =SUM(AO3:AQ3) -> 0 | BG3: =SUM(AS3:BF3) -> 7
A4: ED1-AERO | B4: =COUNTIF(TT!$D$6:$D$15,TALLY!A4) -> 0 | C4: =COUNTIF(TT!$D$22:$D$32,TALLY!A4) -> 0 | D4: =COUNTIF(TT!$D$39:$D$49,TALLY!A4) -> 1 | E4: =COUNTIF(TT!$D$57:$D$67,TALLY!A4) -> 0 | F4: =COUNTIF(TT!$D$74:$D$86,TALLY!A4) -> 0 | G4: =COUNTIF(TT!$D$93:$D$107,TALLY!A4) -> 0 | H4: =COUNTIF(TT!$D$113:$D$129,TALLY!A4) -> 0 | I4: =COUNTIF(TT!$D$135:$D$155,TALLY!A4) -> 0 | J4: =COUNTIF(TT!$D$162:$D$173,TALLY!A4) -> 0 | K4: =COUNTIF(TT!$D$180:$D$199,TALLY!A4) -> 1 | L4: =COUNTIF(TT!$D$207:$D$215,TALLY!A4) -> 0 | M4: =COUNTIF(TT!$D$224:$D$231,TALLY!A4) -> 0 | N4: =COUNTIF(TT!$D$237:$D$249,TALLY!A4) -> 0 | O4: =COUNTIF(TT!$D$256:$D$264,TALLY!A4) -> 0 | P4: =COUNTIF(TT!$D$271:$D$286,TALLY!A4) -> 0 | Q4: =COUNTIF(TT!$D$293:$D$300,TALLY!A4) -> 0 | R4: =COUNTIF(TT!$D$307:$D$319,TALLY!A4) -> 1 | S4: =COUNTIF(TT!$D$326:$D$334,TALLY!A4) -> 0 | T4: =COUNTIF(TT!$D$341:$D$350,TALLY!A4) -> 0 | U4: =COUNTIF(TT!$D$357:$D$366,TALLY!A4) -> 0 | V4: =COUNTIF(TT!$D$373:$D$383,TALLY!A4) -> 0 | W4: =COUNTIF(TT!$D$390:$D$405,TALLY!A4) -> 0 | X4: =COUNTIF(TT!$D$412:$D$423,TALLY!A4) -> 0 | Y4: =COUNTIF(TT!$D$430:$D$438,TALLY!A4) -> 0 | Z4: =COUNTIF(TT!$D$443:$D$457,TALLY!A4) -> 1 | AA4: =COUNTIF(TT!$D$464:$D$474,TALLY!A4) -> 0 | AB4: =COUNTIF(TT!$D$481:$D$494,TALLY!A4) -> 0 | AC4: =COUNTIF(TT!$D$503:$D$522,TALLY!A4) -> 0 | AD4: =COUNTIF(TT!$D$529:$D$541,TALLY!A4) -> 0 | AE4: =COUNTIF(TT!$D$548:$D$561,TALLY!A4) -> 0 | AF4: =COUNTIF(TT!$D$574:$D$584,TALLY!A4) -> 0 | AG4: =COUNTIF(TT!$D$591:$D$601,TALLY!A4) -> 0 | AH4: =COUNTIF(TT!$D$608:$D$619,TALLY!A4) -> 0 | AI4: =COUNTIF(TT!$D$628:$D$647,TALLY!A4) -> 0 | AJ4: =COUNTIF(TT!$D$654:$D$668,TALLY!A4) -> 0 | AK4: =COUNTIF(TT!$D$675:$D$685,TALLY!A4) -> 1 | AL4: =COUNTIF(TT!$D$692:$D$702,TALLY!A4) -> 0 | AM4: =COUNTIF(TT!$D$709:$D$721,TALLY!A4) -> 0 | AN4: =COUNTIF(TT!$D$728:$D$737,TALLY!A4) -> 0 | AO4: =COUNTIF(TT!$D$744:$D$753,TALLY!A4) -> 0 | AP4: =COUNTIF(TT!$D$759:$D$774,TALLY!A4) -> 1 | AQ4: =COUNTIF(TT!$D$781:$D$789,TALLY!A4) -> 0 | AR4: ED1-AERO | AS4: =SUM($B4:$D4) -> 1 | AT4: =SUM(E4:G4) -> 0 | AU4: =SUM(H4:J4) -> 0 | AV4: =SUM(K4:M4) -> 1 | AW4: =SUM(N4:P4) -> 0 | AX4: =SUM($Q4:$S4) -> 1 | AY4: =SUM(T4:V4) -> 0 | AZ4: =SUM(W4:Y4) -> 0 | BA4: =SUM(Z4:AB4) -> 1 | BB4: =SUM(AC4:AE4) -> 0 | BC4: =SUM(AF4:AH4) -> 0 | BD4: =SUM(AI4:AK4) -> 1 | BE4: =SUM(AL4:AN4) -> 0 | BF4: =SUM(AO4:AQ4) -> 1 | BG4: =SUM(AS4:BF4) -> 6
A5: ED1-AUTO | B5: =COUNTIF(TT!$D$6:$D$15,TALLY!A5) -> 0 | C5: =COUNTIF(TT!$D$22:$D$32,TALLY!A5) -> 0 | D5: =COUNTIF(TT!$D$39:$D$49,TALLY!A5) -> 0 | E5: =COUNTIF(TT!$D$57:$D$67,TALLY!A5) -> 0 | F5: =COUNTIF(TT!$D$74:$D$86,TALLY!A5) -> 0 | G5: =COUNTIF(TT!$D$93:$D$107,TALLY!A5) -> 0 | H5: =COUNTIF(TT!$D$113:$D$129,TALLY!A5) -> 1 | I5: =COUNTIF(TT!$D$135:$D$155,TALLY!A5) -> 0 | J5: =COUNTIF(TT!$D$162:$D$173,TALLY!A5) -> 0 | K5: =COUNTIF(TT!$D$180:$D$199,TALLY!A5) -> 0 | L5: =COUNTIF(TT!$D$207:$D$215,TALLY!A5) -> 1 | M5: =COUNTIF(TT!$D$224:$D$231,TALLY!A5) -> 0 | N5: =COUNTIF(TT!$D$237:$D$249,TALLY!A5) -> 0 | O5: =COUNTIF(TT!$D$256:$D$264,TALLY!A5) -> 0 | P5: =COUNTIF(TT!$D$271:$D$286,TALLY!A5) -> 0 | Q5: =COUNTIF(TT!$D$293:$D$300,TALLY!A5) -> 0 | R5: =COUNTIF(TT!$D$307:$D$319,TALLY!A5) -> 1 | S5: =COUNTIF(TT!$D$326:$D$334,TALLY!A5) -> 0 | T5: =COUNTIF(TT!$D$341:$D$350,TALLY!A5) -> 0 | U5: =COUNTIF(TT!$D$357:$D$366,TALLY!A5) -> 0 | V5: =COUNTIF(TT!$D$373:$D$383,TALLY!A5) -> 0 | W5: =COUNTIF(TT!$D$390:$D$405,TALLY!A5) -> 1 | X5: =COUNTIF(TT!$D$412:$D$423,TALLY!A5) -> 0 | Y5: =COUNTIF(TT!$D$430:$D$438,TALLY!A5) -> 0 | Z5: =COUNTIF(TT!$D$443:$D$457,TALLY!A5) -> 0 | AA5: =COUNTIF(TT!$D$464:$D$474,TALLY!A5) -> 0 | AB5: =COUNTIF(TT!$D$481:$D$494,TALLY!A5) -> 0 | AC5: =COUNTIF(TT!$D$503:$D$522,TALLY!A5) -> 0 | AD5: =COUNTIF(TT!$D$529:$D$541,TALLY!A5) -> 1 | AE5: =COUNTIF(TT!$D$548:$D$561,TALLY!A5) -> 0 | AF5: =COUNTIF(TT!$D$574:$D$584,TALLY!A5) -> 0 | AG5: =COUNTIF(TT!$D$591:$D$601,TALLY!A5) -> 0 | AH5: =COUNTIF(TT!$D$608:$D$619,TALLY!A5) -> 0 | AI5: =COUNTIF(TT!$D$628:$D$647,TALLY!A5) -> 0 | AJ5: =COUNTIF(TT!$D$654:$D$668,TALLY!A5) -> 0 | AK5: =COUNTIF(TT!$D$675:$D$685,TALLY!A5) -> 1 | AL5: =COUNTIF(TT!$D$692:$D$702,TALLY!A5) -> 0 | AM5: =COUNTIF(TT!$D$709:$D$721,TALLY!A5) -> 0 | AN5: =COUNTIF(TT!$D$728:$D$737,TALLY!A5) -> 0 | AO5: =COUNTIF(TT!$D$744:$D$753,TALLY!A5) -> 1 | AP5: =COUNTIF(TT!$D$759:$D$774,TALLY!A5) -> 0 | AQ5: =COUNTIF(TT!$D$781:$D$789,TALLY!A5) -> 0 | AR5: ED1-AUTO | AS5: =SUM($B5:$D5) -> 0 | AT5: =SUM(E5:G5) -> 0 | AU5: =SUM(H5:J5) -> 1 | AV5: =SUM(K5:M5) -> 1 | AW5: =SUM(N5:P5) -> 0 | AX5: =SUM($Q5:$S5) -> 1 | AY5: =SUM(T5:V5) -> 0 | AZ5: =SUM(W5:Y5) -> 1 | BA5: =SUM(Z5:AB5) -> 0 | BB5: =SUM(AC5:AE5) -> 1 | BC5: =SUM(AF5:AH5) -> 0 | BD5: =SUM(AI5:AK5) -> 1 | BE5: =SUM(AL5:AN5) -> 0 | BF5: =SUM(AO5:AQ5) -> 1 | BG5: =SUM(AS5:BF5) -> 7
A6: ED1-BME | B6: =COUNTIF(TT!$D$6:$D$15,TALLY!A6) -> 0 | C6: =COUNTIF(TT!$D$22:$D$32,TALLY!A6) -> 0 | D6: =COUNTIF(TT!$D$39:$D$49,TALLY!A6) -> 0 | E6: =COUNTIF(TT!$D$57:$D$67,TALLY!A6) -> 0 | F6: =COUNTIF(TT!$D$74:$D$86,TALLY!A6) -> 1 | G6: =COUNTIF(TT!$D$93:$D$107,TALLY!A6) -> 0 | H6: =COUNTIF(TT!$D$113:$D$129,TALLY!A6) -> 0 | I6: =COUNTIF(TT!$D$135:$D$155,TALLY!A6) -> 0 | J6: =COUNTIF(TT!$D$162:$D$173,TALLY!A6) -> 0 | K6: =COUNTIF(TT!$D$180:$D$199,TALLY!A6) -> 1 | L6: =COUNTIF(TT!$D$207:$D$215,TALLY!A6) -> 0 | M6: =COUNTIF(TT!$D$224:$D$231,TALLY!A6) -> 0 | N6: =COUNTIF(TT!$D$237:$D$249,TALLY!A6) -> 0 | O6: =COUNTIF(TT!$D$256:$D$264,TALLY!A6) -> 0 | P6: =COUNTIF(TT!$D$271:$D$286,TALLY!A6) -> 0 | Q6: =COUNTIF(TT!$D$293:$D$300,TALLY!A6) -> 1 | R6: =COUNTIF(TT!$D$307:$D$319,TALLY!A6) -> 0 | S6: =COUNTIF(TT!$D$326:$D$334,TALLY!A6) -> 0 | T6: =COUNTIF(TT!$D$341:$D$350,TALLY!A6) -> 0 | U6: =COUNTIF(TT!$D$357:$D$366,TALLY!A6) -> 0 | V6: =COUNTIF(TT!$D$373:$D$383,TALLY!A6) -> 1 | W6: =COUNTIF(TT!$D$390:$D$405,TALLY!A6) -> 0 | X6: =COUNTIF(TT!$D$412:$D$423,TALLY!A6) -> 0 | Y6: =COUNTIF(TT!$D$430:$D$438,TALLY!A6) -> 0 | Z6: =COUNTIF(TT!$D$443:$D$457,TALLY!A6) -> 0 | AA6: =COUNTIF(TT!$D$464:$D$474,TALLY!A6) -> 0 | AB6: =COUNTIF(TT!$D$481:$D$494,TALLY!A6) -> 0 | AC6: =COUNTIF(TT!$D$503:$D$522,TALLY!A6) -> 0 | AD6: =COUNTIF(TT!$D$529:$D$541,TALLY!A6) -> 0 | AE6: =COUNTIF(TT!$D$548:$D$561,TALLY!A6) -> 0 | AF6: =COUNTIF(TT!$D$574:$D$584,TALLY!A6) -> 0 | AG6: =COUNTIF(TT!$D$591:$D$601,TALLY!A6) -> 0 | AH6: =COUNTIF(TT!$D$608:$D$619,TALLY!A6) -> 0 | AI6: =COUNTIF(TT!$D$628:$D$647,TALLY!A6) -> 0 | AJ6: =COUNTIF(TT!$D$654:$D$668,TALLY!A6) -> 1 | AK6: =COUNTIF(TT!$D$675:$D$685,TALLY!A6) -> 0 | AL6: =COUNTIF(TT!$D$692:$D$702,TALLY!A6) -> 0 | AM6: =COUNTIF(TT!$D$709:$D$721,TALLY!A6) -> 1 | AN6: =COUNTIF(TT!$D$728:$D$737,TALLY!A6) -> 0 | AO6: =COUNTIF(TT!$D$744:$D$753,TALLY!A6) -> 0 | AP6: =COUNTIF(TT!$D$759:$D$774,TALLY!A6) -> 0 | AQ6: =COUNTIF(TT!$D$781:$D$789,TALLY!A6) -> 0 | AR6: ED1-BME | AS6: =SUM($B6:$D6) -> 0 | AT6: =SUM(E6:G6) -> 1 | AU6: =SUM(H6:J6) -> 0 | AV6: =SUM(K6:M6) -> 1 | AW6: =SUM(N6:P6) -> 0 | AX6: =SUM($Q6:$S6) -> 1 | AY6: =SUM(T6:V6) -> 1 | AZ6: =SUM(W6:Y6) -> 0 | BA6: =SUM(Z6:AB6) -> 0 | BB6: =SUM(AC6:AE6) -> 0 | BC6: =SUM(AF6:AH6) -> 0 | BD6: =SUM(AI6:AK6) -> 1 | BE6: =SUM(AL6:AN6) -> 1 | BF6: =SUM(AO6:AQ6) -> 0 | BG6: =SUM(AS6:BF6) -> 6
A7: ED1-CE | B7: =COUNTIF(TT!$D$6:$D$15,TALLY!A7) -> 0 | C7: =COUNTIF(TT!$D$22:$D$32,TALLY!A7) -> 1 | D7: =COUNTIF(TT!$D$39:$D$49,TALLY!A7) -> 0 | E7: =COUNTIF(TT!$D$57:$D$67,TALLY!A7) -> 0 | F7: =COUNTIF(TT!$D$74:$D$86,TALLY!A7) -> 0 | G7: =COUNTIF(TT!$D$93:$D$107,TALLY!A7) -> 0 | H7: =COUNTIF(TT!$D$113:$D$129,TALLY!A7) -> 1 | I7: =COUNTIF(TT!$D$135:$D$155,TALLY!A7) -> 0 | J7: =COUNTIF(TT!$D$162:$D$173,TALLY!A7) -> 0 | K7: =COUNTIF(TT!$D$180:$D$199,TALLY!A7) -> 0 | L7: =COUNTIF(TT!$D$207:$D$215,TALLY!A7) -> 1 | M7: =COUNTIF(TT!$D$224:$D$231,TALLY!A7) -> 0 | N7: =COUNTIF(TT!$D$237:$D$249,TALLY!A7) -> 1 | O7: =COUNTIF(TT!$D$256:$D$264,TALLY!A7) -> 0 | P7: =COUNTIF(TT!$D$271:$D$286,TALLY!A7) -> 0 | Q7: =COUNTIF(TT!$D$293:$D$300,TALLY!A7) -> 0 | R7: =COUNTIF(TT!$D$307:$D$319,TALLY!A7) -> 0 | S7: =COUNTIF(TT!$D$326:$D$334,TALLY!A7) -> 0 | T7: =COUNTIF(TT!$D$341:$D$350,TALLY!A7) -> 1 | U7: =COUNTIF(TT!$D$357:$D$366,TALLY!A7) -> 0 | V7: =COUNTIF(TT!$D$373:$D$383,TALLY!A7) -> 0 | W7: =COUNTIF(TT!$D$390:$D$405,TALLY!A7) -> 0 | X7: =COUNTIF(TT!$D$412:$D$423,TALLY!A7) -> 0 | Y7: =COUNTIF(TT!$D$430:$D$438,TALLY!A7) -> 1 | Z7: =COUNTIF(TT!$D$443:$D$457,TALLY!A7) -> 0 | AA7: =COUNTIF(TT!$D$464:$D$474,TALLY!A7) -> 0 | AB7: =COUNTIF(TT!$D$481:$D$494,TALLY!A7) -> 0 | AC7: =COUNTIF(TT!$D$503:$D$522,TALLY!A7) -> 1 | AD7: =COUNTIF(TT!$D$529:$D$541,TALLY!A7) -> 0 | AE7: =COUNTIF(TT!$D$548:$D$561,TALLY!A7) -> 0 | AF7: =COUNTIF(TT!$D$574:$D$584,TALLY!A7) -> 0 | AG7: =COUNTIF(TT!$D$591:$D$601,TALLY!A7) -> 0 | AH7: =COUNTIF(TT!$D$608:$D$619,TALLY!A7) -> 0 | AI7: =COUNTIF(TT!$D$628:$D$647,TALLY!A7) -> 1 | AJ7: =COUNTIF(TT!$D$654:$D$668,TALLY!A7) -> 0 | AK7: =COUNTIF(TT!$D$675:$D$685,TALLY!A7) -> 0 | AL7: =COUNTIF(TT!$D$692:$D$702,TALLY!A7) -> 0 | AM7: =COUNTIF(TT!$D$709:$D$721,TALLY!A7) -> 1 | AN7: =COUNTIF(TT!$D$728:$D$737,TALLY!A7) -> 0 | AO7: =COUNTIF(TT!$D$744:$D$753,TALLY!A7) -> 0 | AP7: =COUNTIF(TT!$D$759:$D$774,TALLY!A7) -> 0 | AQ7: =COUNTIF(TT!$D$781:$D$789,TALLY!A7) -> 0 | AR7: ED1-CE | AS7: =SUM($B7:$D7) -> 1 | AT7: =SUM(E7:G7) -> 0 | AU7: =SUM(H7:J7) -> 1 | AV7: =SUM(K7:M7) -> 1 | AW7: =SUM(N7:P7) -> 1 | AX7: =SUM($Q7:$S7) -> 0 | AY7: =SUM(T7:V7) -> 1 | AZ7: =SUM(W7:Y7) -> 1 | BA7: =SUM(Z7:AB7) -> 0 | BB7: =SUM(AC7:AE7) -> 1 | BC7: =SUM(AF7:AH7) -> 0 | BD7: =SUM(AI7:AK7) -> 1 | BE7: =SUM(AL7:AN7) -> 1 | BF7: =SUM(AO7:AQ7) -> 0 | BG7: =SUM(AS7:BF7) -> 9
A8: ED1-CHE | B8: =COUNTIF(TT!$D$6:$D$15,TALLY!A8) -> 1 | C8: =COUNTIF(TT!$D$22:$D$32,TALLY!A8) -> 0 | D8: =COUNTIF(TT!$D$39:$D$49,TALLY!A8) -> 0 | E8: =COUNTIF(TT!$D$57:$D$67,TALLY!A8) -> 0 | F8: =COUNTIF(TT!$D$74:$D$86,TALLY!A8) -> 0 | G8: =COUNTIF(TT!$D$93:$D$107,TALLY!A8) -> 0 | H8: =COUNTIF(TT!$D$113:$D$129,TALLY!A8) -> 0 | I8: =COUNTIF(TT!$D$135:$D$155,TALLY!A8) -> 0 | J8: =COUNTIF(TT!$D$162:$D$173,TALLY!A8) -> 0 | K8: =COUNTIF(TT!$D$180:$D$199,TALLY!A8) -> 1 | L8: =COUNTIF(TT!$D$207:$D$215,TALLY!A8) -> 0 | M8: =COUNTIF(TT!$D$224:$D$231,TALLY!A8) -> 0 | N8: =COUNTIF(TT!$D$237:$D$249,TALLY!A8) -> 1 | O8: =COUNTIF(TT!$D$256:$D$264,TALLY!A8) -> 0 | P8: =COUNTIF(TT!$D$271:$D$286,TALLY!A8) -> 0 | Q8: =COUNTIF(TT!$D$293:$D$300,TALLY!A8) -> 0 | R8: =COUNTIF(TT!$D$307:$D$319,TALLY!A8) -> 1 | S8: =COUNTIF(TT!$D$326:$D$334,TALLY!A8) -> 0 | T8: =COUNTIF(TT!$D$341:$D$350,TALLY!A8) -> 0 | U8: =COUNTIF(TT!$D$357:$D$366,TALLY!A8) -> 0 | V8: =COUNTIF(TT!$D$373:$D$383,TALLY!A8) -> 0 | W8: =COUNTIF(TT!$D$390:$D$405,TALLY!A8) -> 0 | X8: =COUNTIF(TT!$D$412:$D$423,TALLY!A8) -> 0 | Y8: =COUNTIF(TT!$D$430:$D$438,TALLY!A8) -> 0 | Z8: =COUNTIF(TT!$D$443:$D$457,TALLY!A8) -> 0 | AA8: =COUNTIF(TT!$D$464:$D$474,TALLY!A8) -> 0 | AB8: =COUNTIF(TT!$D$481:$D$494,TALLY!A8) -> 0 | AC8: =COUNTIF(TT!$D$503:$D$522,TALLY!A8) -> 0 | AD8: =COUNTIF(TT!$D$529:$D$541,TALLY!A8) -> 0 | AE8: =COUNTIF(TT!$D$548:$D$561,TALLY!A8) -> 0 | AF8: =COUNTIF(TT!$D$574:$D$584,TALLY!A8) -> 0 | AG8: =COUNTIF(TT!$D$591:$D$601,TALLY!A8) -> 0 | AH8: =COUNTIF(TT!$D$608:$D$619,TALLY!A8) -> 0 | AI8: =COUNTIF(TT!$D$628:$D$647,TALLY!A8) -> 0 | AJ8: =COUNTIF(TT!$D$654:$D$668,TALLY!A8) -> 1 | AK8: =COUNTIF(TT!$D$675:$D$685,TALLY!A8) -> 0 | AL8: =COUNTIF(TT!$D$692:$D$702,TALLY!A8) -> 1 | AM8: =COUNTIF(TT!$D$709:$D$721,TALLY!A8) -> 0 | AN8: =COUNTIF(TT!$D$728:$D$737,TALLY!A8) -> 0 | AO8: =COUNTIF(TT!$D$744:$D$753,TALLY!A8) -> 0 | AP8: =COUNTIF(TT!$D$759:$D$774,TALLY!A8) -> 1 | AQ8: =COUNTIF(TT!$D$781:$D$789,TALLY!A8) -> 0 | AR8: ED1-CHE | AS8: =SUM($B8:$D8) -> 1 | AT8: =SUM(E8:G8) -> 0 | AU8: =SUM(H8:J8) -> 0 | AV8: =SUM(K8:M8) -> 1 | AW8: =SUM(N8:P8) -> 1 | AX8: =SUM($Q8:$S8) -> 1 | AY8: =SUM(T8:V8) -> 0 | AZ8: =SUM(W8:Y8) -> 0 | BA8: =SUM(Z8:AB8) -> 0 | BB8: =SUM(AC8:AE8) -> 0 | BC8: =SUM(AF8:AH8) -> 0 | BD8: =SUM(AI8:AK8) -> 1 | BE8: =SUM(AL8:AN8) -> 1 | BF8: =SUM(AO8:AQ8) -> 1 | BG8: =SUM(AS8:BF8) -> 7
A9: ED1-COE | B9: =COUNTIF(TT!$D$6:$D$15,TALLY!A9) -> 0 | C9: =COUNTIF(TT!$D$22:$D$32,TALLY!A9) -> 0 | D9: =COUNTIF(TT!$D$39:$D$49,TALLY!A9) -> 1 | E9: =COUNTIF(TT!$D$57:$D$67,TALLY!A9) -> 0 | F9: =COUNTIF(TT!$D$74:$D$86,TALLY!A9) -> 0 | G9: =COUNTIF(TT!$D$93:$D$107,TALLY!A9) -> 0 | H9: =COUNTIF(TT!$D$113:$D$129,TALLY!A9) -> 0 | I9: =COUNTIF(TT!$D$135:$D$155,TALLY!A9) -> 0 | J9: =COUNTIF(TT!$D$162:$D$173,TALLY!A9) -> 0 | K9: =COUNTIF(TT!$D$180:$D$199,TALLY!A9) -> 0 | L9: =COUNTIF(TT!$D$207:$D$215,TALLY!A9) -> 1 | M9: =COUNTIF(TT!$D$224:$D$231,TALLY!A9) -> 0 | N9: =COUNTIF(TT!$D$237:$D$249,TALLY!A9) -> 0 | O9: =COUNTIF(TT!$D$256:$D$264,TALLY!A9) -> 0 | P9: =COUNTIF(TT!$D$271:$D$286,TALLY!A9) -> 0 | Q9: =COUNTIF(TT!$D$293:$D$300,TALLY!A9) -> 1 | R9: =COUNTIF(TT!$D$307:$D$319,TALLY!A9) -> 0 | S9: =COUNTIF(TT!$D$326:$D$334,TALLY!A9) -> 0 | T9: =COUNTIF(TT!$D$341:$D$350,TALLY!A9) -> 0 | U9: =COUNTIF(TT!$D$357:$D$366,TALLY!A9) -> 0 | V9: =COUNTIF(TT!$D$373:$D$383,TALLY!A9) -> 1 | W9: =COUNTIF(TT!$D$390:$D$405,TALLY!A9) -> 0 | X9: =COUNTIF(TT!$D$412:$D$423,TALLY!A9) -> 0 | Y9: =COUNTIF(TT!$D$430:$D$438,TALLY!A9) -> 1 | Z9: =COUNTIF(TT!$D$443:$D$457,TALLY!A9) -> 0 | AA9: =COUNTIF(TT!$D$464:$D$474,TALLY!A9) -> 0 | AB9: =COUNTIF(TT!$D$481:$D$494,TALLY!A9) -> 0 | AC9: =COUNTIF(TT!$D$503:$D$522,TALLY!A9) -> 0 | AD9: =COUNTIF(TT!$D$529:$D$541,TALLY!A9) -> 0 | AE9: =COUNTIF(TT!$D$548:$D$561,TALLY!A9) -> 0 | AF9: =COUNTIF(TT!$D$574:$D$584,TALLY!A9) -> 0 | AG9: =COUNTIF(TT!$D$591:$D$601,TALLY!A9) -> 0 | AH9: =COUNTIF(TT!$D$608:$D$619,TALLY!A9) -> 0 | AI9: =COUNTIF(TT!$D$628:$D$647,TALLY!A9) -> 0 | AJ9: =COUNTIF(TT!$D$654:$D$668,TALLY!A9) -> 1 | AK9: =COUNTIF(TT!$D$675:$D$685,TALLY!A9) -> 0 | AL9: =COUNTIF(TT!$D$692:$D$702,TALLY!A9) -> 0 | AM9: =COUNTIF(TT!$D$709:$D$721,TALLY!A9) -> 0 | AN9: =COUNTIF(TT!$D$728:$D$737,TALLY!A9) -> 0 | AO9: =COUNTIF(TT!$D$744:$D$753,TALLY!A9) -> 0 | AP9: =COUNTIF(TT!$D$759:$D$774,TALLY!A9) -> 0 | AQ9: =COUNTIF(TT!$D$781:$D$789,TALLY!A9) -> 0 | AR9: ED1-COE | AS9: =SUM($B9:$D9) -> 1 | AT9: =SUM(E9:G9) -> 0 | AU9: =SUM(H9:J9) -> 0 | AV9: =SUM(K9:M9) -> 1 | AW9: =SUM(N9:P9) -> 0 | AX9: =SUM($Q9:$S9) -> 1 | AY9: =SUM(T9:V9) -> 1 | AZ9: =SUM(W9:Y9) -> 1 | BA9: =SUM(Z9:AB9) -> 0 | BB9: =SUM(AC9:AE9) -> 0 | BC9: =SUM(AF9:AH9) -> 0 | BD9: =SUM(AI9:AK9) -> 1 | BE9: =SUM(AL9:AN9) -> 0 | BF9: =SUM(AO9:AQ9) -> 0 | BG9: =SUM(AS9:BF9) -> 6
A10: ED1-EE | B10: =COUNTIF(TT!$D$6:$D$15,TALLY!A10) -> 0 | C10: =COUNTIF(TT!$D$22:$D$32,TALLY!A10) -> 0 | D10: =COUNTIF(TT!$D$39:$D$49,TALLY!A10) -> 0 | E10: =COUNTIF(TT!$D$57:$D$67,TALLY!A10) -> 0 | F10: =COUNTIF(TT!$D$74:$D$86,TALLY!A10) -> 0 | G10: =COUNTIF(TT!$D$93:$D$107,TALLY!A10) -> 0 | H10: =COUNTIF(TT!$D$113:$D$129,TALLY!A10) -> 1 | I10: =COUNTIF(TT!$D$135:$D$155,TALLY!A10) -> 0 | J10: =COUNTIF(TT!$D$162:$D$173,TALLY!A10) -> 0 | K10: =COUNTIF(TT!$D$180:$D$199,TALLY!A10) -> 1 | L10: =COUNTIF(TT!$D$207:$D$215,TALLY!A10) -> 0 | M10: =COUNTIF(TT!$D$224:$D$231,TALLY!A10) -> 0 | N10: =COUNTIF(TT!$D$237:$D$249,TALLY!A10) -> 0 | O10: =COUNTIF(TT!$D$256:$D$264,TALLY!A10) -> 1 | P10: =COUNTIF(TT!$D$271:$D$286,TALLY!A10) -> 0 | Q10: =COUNTIF(TT!$D$293:$D$300,TALLY!A10) -> 1 | R10: =COUNTIF(TT!$D$307:$D$319,TALLY!A10) -> 0 | S10: =COUNTIF(TT!$D$326:$D$334,TALLY!A10) -> 0 | T10: =COUNTIF(TT!$D$341:$D$350,TALLY!A10) -> 0 | U10: =COUNTIF(TT!$D$357:$D$366,TALLY!A10) -> 0 | V10: =COUNTIF(TT!$D$373:$D$383,TALLY!A10) -> 0 | W10: =COUNTIF(TT!$D$390:$D$405,TALLY!A10) -> 1 | X10: =COUNTIF(TT!$D$412:$D$423,TALLY!A10) -> 0 | Y10: =COUNTIF(TT!$D$430:$D$438,TALLY!A10) -> 0 | Z10: =COUNTIF(TT!$D$443:$D$457,TALLY!A10) -> 0 | AA10: =COUNTIF(TT!$D$464:$D$474,TALLY!A10) -> 0 | AB10: =COUNTIF(TT!$D$481:$D$494,TALLY!A10) -> 0 | AC10: =COUNTIF(TT!$D$503:$D$522,TALLY!A10) -> 0 | AD10: =COUNTIF(TT!$D$529:$D$541,TALLY!A10) -> 0 | AE10: =COUNTIF(TT!$D$548:$D$561,TALLY!A10) -> 1 | AF10: =COUNTIF(TT!$D$574:$D$584,TALLY!A10) -> 0 | AG10: =COUNTIF(TT!$D$591:$D$601,TALLY!A10) -> 0 | AH10: =COUNTIF(TT!$D$608:$D$619,TALLY!A10) -> 0 | AI10: =COUNTIF(TT!$D$628:$D$647,TALLY!A10) -> 0 | AJ10: =COUNTIF(TT!$D$654:$D$668,TALLY!A10) -> 0 | AK10: =COUNTIF(TT!$D$675:$D$685,TALLY!A10) -> 1 | AL10: =COUNTIF(TT!$D$692:$D$702,TALLY!A10) -> 0 | AM10: =COUNTIF(TT!$D$709:$D$721,TALLY!A10) -> 0 | AN10: =COUNTIF(TT!$D$728:$D$737,TALLY!A10) -> 0 | AO10: =COUNTIF(TT!$D$744:$D$753,TALLY!A10) -> 0 | AP10: =COUNTIF(TT!$D$759:$D$774,TALLY!A10) -> 0 | AQ10: =COUNTIF(TT!$D$781:$D$789,TALLY!A10) -> 0 | AR10: ED1-EE | AS10: =SUM($B10:$D10) -> 0 | AT10: =SUM(E10:G10) -> 0 | AU10: =SUM(H10:J10) -> 1 | AV10: =SUM(K10:M10) -> 1 | AW10: =SUM(N10:P10) -> 1 | AX10: =SUM($Q10:$S10) -> 1 | AY10: =SUM(T10:V10) -> 0 | AZ10: =SUM(W10:Y10) -> 1 | BA10: =SUM(Z10:AB10) -> 0 | BB10: =SUM(AC10:AE10) -> 1 | BC10: =SUM(AF10:AH10) -> 0 | BD10: =SUM(AI10:AK10) -> 1 | BE10: =SUM(AL10:AN10) -> 0 | BF10: =SUM(AO10:AQ10) -> 0 | BG10: =SUM(AS10:BF10) -> 7
A11: ED1-GEOL | B11: =COUNTIF(TT!$D$6:$D$15,TALLY!A11) -> 0 | C11: =COUNTIF(TT!$D$22:$D$32,TALLY!A11) -> 1 | D11: =COUNTIF(TT!$D$39:$D$49,TALLY!A11) -> 0 | E11: =COUNTIF(TT!$D$57:$D$67,TALLY!A11) -> 0 | F11: =COUNTIF(TT!$D$74:$D$86,TALLY!A11) -> 0 | G11: =COUNTIF(TT!$D$93:$D$107,TALLY!A11) -> 0 | H11: =COUNTIF(TT!$D$113:$D$129,TALLY!A11) -> 1 | I11: =COUNTIF(TT!$D$135:$D$155,TALLY!A11) -> 0 | J11: =COUNTIF(TT!$D$162:$D$173,TALLY!A11) -> 0 | K11: =COUNTIF(TT!$D$180:$D$199,TALLY!A11) -> 0 | L11: =COUNTIF(TT!$D$207:$D$215,TALLY!A11) -> 1 | M11: =COUNTIF(TT!$D$224:$D$231,TALLY!A11) -> 0 | N11: =COUNTIF(TT!$D$237:$D$249,TALLY!A11) -> 1 | O11: =COUNTIF(TT!$D$256:$D$264,TALLY!A11) -> 0 | P11: =COUNTIF(TT!$D$271:$D$286,TALLY!A11) -> 0 | Q11: =COUNTIF(TT!$D$293:$D$300,TALLY!A11) -> 0 | R11: =COUNTIF(TT!$D$307:$D$319,TALLY!A11) -> 0 | S11: =COUNTIF(TT!$D$326:$D$334,TALLY!A11) -> 0 | T11: =COUNTIF(TT!$D$341:$D$350,TALLY!A11) -> 0 | U11: =COUNTIF(TT!$D$357:$D$366,TALLY!A11) -> 0 | V11: =COUNTIF(TT!$D$373:$D$383,TALLY!A11) -> 1 | W11: =COUNTIF(TT!$D$390:$D$405,TALLY!A11) -> 0 | X11: =COUNTIF(TT!$D$412:$D$423,TALLY!A11) -> 0 | Y11: =COUNTIF(TT!$D$430:$D$438,TALLY!A11) -> 1 | Z11: =COUNTIF(TT!$D$443:$D$457,TALLY!A11) -> 0 | AA11: =COUNTIF(TT!$D$464:$D$474,TALLY!A11) -> 0 | AB11: =COUNTIF(TT!$D$481:$D$494,TALLY!A11) -> 0 | AC11: =COUNTIF(TT!$D$503:$D$522,TALLY!A11) -> 1 | AD11: =COUNTIF(TT!$D$529:$D$541,TALLY!A11) -> 0 | AE11: =COUNTIF(TT!$D$548:$D$561,TALLY!A11) -> 0 | AF11: =COUNTIF(TT!$D$574:$D$584,TALLY!A11) -> 0 | AG11: =COUNTIF(TT!$D$591:$D$601,TALLY!A11) -> 0 | AH11: =COUNTIF(TT!$D$608:$D$619,TALLY!A11) -> 0 | AI11: =COUNTIF(TT!$D$628:$D$647,TALLY!A11) -> 1 | AJ11: =COUNTIF(TT!$D$654:$D$668,TALLY!A11) -> 0 | AK11: =COUNTIF(TT!$D$675:$D$685,TALLY!A11) -> 0 | AL11: =COUNTIF(TT!$D$692:$D$702,TALLY!A11) -> 0 | AM11: =COUNTIF(TT!$D$709:$D$721,TALLY!A11) -> 1 | AN11: =COUNTIF(TT!$D$728:$D$737,TALLY!A11) -> 0 | AO11: =COUNTIF(TT!$D$744:$D$753,TALLY!A11) -> 0 | AP11: =COUNTIF(TT!$D$759:$D$774,TALLY!A11) -> 1 | AQ11: =COUNTIF(TT!$D$781:$D$789,TALLY!A11) -> 0 | AR11: ED1-GEOL | AS11: =SUM($B11:$D11) -> 1 | AT11: =SUM(E11:G11) -> 0 | AU11: =SUM(H11:J11) -> 1 | AV11: =SUM(K11:M11) -> 1 | AW11: =SUM(N11:P11) -> 1 | AX11: =SUM($Q11:$S11) -> 0 | AY11: =SUM(T11:V11) -> 1 | AZ11: =SUM(W11:Y11) -> 1 | BA11: =SUM(Z11:AB11) -> 0 | BB11: =SUM(AC11:AE11) -> 1 | BC11: =SUM(AF11:AH11) -> 0 | BD11: =SUM(AI11:AK11) -> 1 | BE11: =SUM(AL11:AN11) -> 1 | BF11: =SUM(AO11:AQ11) -> 1 | BG11: =SUM(AS11:BF11) -> 10
A12: ED1-GEOM | B12: =COUNTIF(TT!$D$6:$D$15,TALLY!A12) -> 0 | C12: =COUNTIF(TT!$D$22:$D$32,TALLY!A12) -> 0 | D12: =COUNTIF(TT!$D$39:$D$49,TALLY!A12) -> 0 | E12: =COUNTIF(TT!$D$57:$D$67,TALLY!A12) -> 0 | F12: =COUNTIF(TT!$D$74:$D$86,TALLY!A12) -> 0 | G12: =COUNTIF(TT!$D$93:$D$107,TALLY!A12) -> 0 | H12: =COUNTIF(TT!$D$113:$D$129,TALLY!A12) -> 0 | I12: =COUNTIF(TT!$D$135:$D$155,TALLY!A12) -> 1 | J12: =COUNTIF(TT!$D$162:$D$173,TALLY!A12) -> 0 | K12: =COUNTIF(TT!$D$180:$D$199,TALLY!A12) -> 0 | L12: =COUNTIF(TT!$D$207:$D$215,TALLY!A12) -> 1 | M12: =COUNTIF(TT!$D$224:$D$231,TALLY!A12) -> 0 | N12: =COUNTIF(TT!$D$237:$D$249,TALLY!A12) -> 0 | O12: =COUNTIF(TT!$D$256:$D$264,TALLY!A12) -> 1 | P12: =COUNTIF(TT!$D$271:$D$286,TALLY!A12) -> 0 | Q12: =COUNTIF(TT!$D$293:$D$300,TALLY!A12) -> 0 | R12: =COUNTIF(TT!$D$307:$D$319,TALLY!A12) -> 0 | S12: =COUNTIF(TT!$D$326:$D$334,TALLY!A12) -> 0 | T12: =COUNTIF(TT!$D$341:$D$350,TALLY!A12) -> 0 | U12: =COUNTIF(TT!$D$357:$D$366,TALLY!A12) -> 0 | V12: =COUNTIF(TT!$D$373:$D$383,TALLY!A12) -> 0 | W12: =COUNTIF(TT!$D$390:$D$405,TALLY!A12) -> 0 | X12: =COUNTIF(TT!$D$412:$D$423,TALLY!A12) -> 0 | Y12: =COUNTIF(TT!$D$430:$D$438,TALLY!A12) -> 0 | Z12: =COUNTIF(TT!$D$443:$D$457,TALLY!A12) -> 1 | AA12: =COUNTIF(TT!$D$464:$D$474,TALLY!A12) -> 0 | AB12: =COUNTIF(TT!$D$481:$D$494,TALLY!A12) -> 0 | AC12: =COUNTIF(TT!$D$503:$D$522,TALLY!A12) -> 0 | AD12: =COUNTIF(TT!$D$529:$D$541,TALLY!A12) -> 1 | AE12: =COUNTIF(TT!$D$548:$D$561,TALLY!A12) -> 0 | AF12: =COUNTIF(TT!$D$574:$D$584,TALLY!A12) -> 0 | AG12: =COUNTIF(TT!$D$591:$D$601,TALLY!A12) -> 0 | AH12: =COUNTIF(TT!$D$608:$D$619,TALLY!A12) -> 0 | AI12: =COUNTIF(TT!$D$628:$D$647,TALLY!A12) -> 0 | AJ12: =COUNTIF(TT!$D$654:$D$668,TALLY!A12) -> 1 | AK12: =COUNTIF(TT!$D$675:$D$685,TALLY!A12) -> 0 | AL12: =COUNTIF(TT!$D$692:$D$702,TALLY!A12) -> 0 | AM12: =COUNTIF(TT!$D$709:$D$721,TALLY!A12) -> 0 | AN12: =COUNTIF(TT!$D$728:$D$737,TALLY!A12) -> 1 | AO12: =COUNTIF(TT!$D$744:$D$753,TALLY!A12) -> 0 | AP12: =COUNTIF(TT!$D$759:$D$774,TALLY!A12) -> 0 | AQ12: =COUNTIF(TT!$D$781:$D$789,TALLY!A12) -> 0 | AR12: ED1-GEOM | AS12: =SUM($B12:$D12) -> 0 | AT12: =SUM(E12:G12) -> 0 | AU12: =SUM(H12:J12) -> 1 | AV12: =SUM(K12:M12) -> 1 | AW12: =SUM(N12:P12) -> 1 | AX12: =SUM($Q12:$S12) -> 0 | AY12: =SUM(T12:V12) -> 0 | AZ12: =SUM(W12:Y12) -> 0 | BA12: =SUM(Z12:AB12) -> 1 | BB12: =SUM(AC12:AE12) -> 1 | BC12: =SUM(AF12:AH12) -> 0 | BD12: =SUM(AI12:AK12) -> 1 | BE12: =SUM(AL12:AN12) -> 1 | BF12: =SUM(AO12:AQ12) -> 0 | BG12: =SUM(AS12:BF12) -> 7
A13: ED1-IND | B13: =COUNTIF(TT!$D$6:$D$15,TALLY!A13) -> 0 | C13: =COUNTIF(TT!$D$22:$D$32,TALLY!A13) -> 0 | D13: =COUNTIF(TT!$D$39:$D$49,TALLY!A13) -> 1 | E13: =COUNTIF(TT!$D$57:$D$67,TALLY!A13) -> 0 | F13: =COUNTIF(TT!$D$74:$D$86,TALLY!A13) -> 0 | G13: =COUNTIF(TT!$D$93:$D$107,TALLY!A13) -> 0 | H13: =COUNTIF(TT!$D$113:$D$129,TALLY!A13) -> 0 | I13: =COUNTIF(TT!$D$135:$D$155,TALLY!A13) -> 0 | J13: =COUNTIF(TT!$D$162:$D$173,TALLY!A13) -> 0 | K13: =COUNTIF(TT!$D$180:$D$199,TALLY!A13) -> 1 | L13: =COUNTIF(TT!$D$207:$D$215,TALLY!A13) -> 0 | M13: =COUNTIF(TT!$D$224:$D$231,TALLY!A13) -> 0 | N13: =COUNTIF(TT!$D$237:$D$249,TALLY!A13) -> 0 | O13: =COUNTIF(TT!$D$256:$D$264,TALLY!A13) -> 0 | P13: =COUNTIF(TT!$D$271:$D$286,TALLY!A13) -> 0 | Q13: =COUNTIF(TT!$D$293:$D$300,TALLY!A13) -> 0 | R13: =COUNTIF(TT!$D$307:$D$319,TALLY!A13) -> 1 | S13: =COUNTIF(TT!$D$326:$D$334,TALLY!A13) -> 0 | T13: =COUNTIF(TT!$D$341:$D$350,TALLY!A13) -> 0 | U13: =COUNTIF(TT!$D$357:$D$366,TALLY!A13) -> 0 | V13: =COUNTIF(TT!$D$373:$D$383,TALLY!A13) -> 0 | W13: =COUNTIF(TT!$D$390:$D$405,TALLY!A13) -> 1 | X13: =COUNTIF(TT!$D$412:$D$423,TALLY!A13) -> 0 | Y13: =COUNTIF(TT!$D$430:$D$438,TALLY!A13) -> 0 | Z13: =COUNTIF(TT!$D$443:$D$457,TALLY!A13) -> 0 | AA13: =COUNTIF(TT!$D$464:$D$474,TALLY!A13) -> 0 | AB13: =COUNTIF(TT!$D$481:$D$494,TALLY!A13) -> 0 | AC13: =COUNTIF(TT!$D$503:$D$522,TALLY!A13) -> 0 | AD13: =COUNTIF(TT!$D$529:$D$541,TALLY!A13) -> 1 | AE13: =COUNTIF(TT!$D$548:$D$561,TALLY!A13) -> 0 | AF13: =COUNTIF(TT!$D$574:$D$584,TALLY!A13) -> 0 | AG13: =COUNTIF(TT!$D$591:$D$601,TALLY!A13) -> 0 | AH13: =COUNTIF(TT!$D$608:$D$619,TALLY!A13) -> 0 | AI13: =COUNTIF(TT!$D$628:$D$647,TALLY!A13) -> 0 | AJ13: =COUNTIF(TT!$D$654:$D$668,TALLY!A13) -> 1 | AK13: =COUNTIF(TT!$D$675:$D$685,TALLY!A13) -> 0 | AL13: =COUNTIF(TT!$D$692:$D$702,TALLY!A13) -> 0 | AM13: =COUNTIF(TT!$D$709:$D$721,TALLY!A13) -> 0 | AN13: =COUNTIF(TT!$D$728:$D$737,TALLY!A13) -> 0 | AO13: =COUNTIF(TT!$D$744:$D$753,TALLY!A13) -> 0 | AP13: =COUNTIF(TT!$D$759:$D$774,TALLY!A13) -> 1 | AQ13: =COUNTIF(TT!$D$781:$D$789,TALLY!A13) -> 0 | AR13: ED1-IND | AS13: =SUM($B13:$D13) -> 1 | AT13: =SUM(E13:G13) -> 0 | AU13: =SUM(H13:J13) -> 0 | AV13: =SUM(K13:M13) -> 1 | AW13: =SUM(N13:P13) -> 0 | AX13: =SUM($Q13:$S13) -> 1 | AY13: =SUM(T13:V13) -> 0 | AZ13: =SUM(W13:Y13) -> 1 | BA13: =SUM(Z13:AB13) -> 0 | BB13: =SUM(AC13:AE13) -> 1 | BC13: =SUM(AF13:AH13) -> 0 | BD13: =SUM(AI13:AK13) -> 1 | BE13: =SUM(AL13:AN13) -> 0 | BF13: =SUM(AO13:AQ13) -> 1 | BG13: =SUM(AS13:BF13) -> 7
A14: ED1-MARI | B14: =COUNTIF(TT!$D$6:$D$15,TALLY!A14) -> 0 | C14: =COUNTIF(TT!$D$22:$D$32,TALLY!A14) -> 0 | D14: =COUNTIF(TT!$D$39:$D$49,TALLY!A14) -> 0 | E14: =COUNTIF(TT!$D$57:$D$67,TALLY!A14) -> 0 | F14: =COUNTIF(TT!$D$74:$D$86,TALLY!A14) -> 0 | G14: =COUNTIF(TT!$D$93:$D$107,TALLY!A14) -> 1 | H14: =COUNTIF(TT!$D$113:$D$129,TALLY!A14) -> 0 | I14: =COUNTIF(TT!$D$135:$D$155,TALLY!A14) -> 0 | J14: =COUNTIF(TT!$D$162:$D$173,TALLY!A14) -> 0 | K14: =COUNTIF(TT!$D$180:$D$199,TALLY!A14) -> 1 | L14: =COUNTIF(TT!$D$207:$D$215,TALLY!A14) -> 0 | M14: =COUNTIF(TT!$D$224:$D$231,TALLY!A14) -> 0 | N14: =COUNTIF(TT!$D$237:$D$249,TALLY!A14) -> 0 | O14: =COUNTIF(TT!$D$256:$D$264,TALLY!A14) -> 0 | P14: =COUNTIF(TT!$D$271:$D$286,TALLY!A14) -> 0 | Q14: =COUNTIF(TT!$D$293:$D$300,TALLY!A14) -> 0 | R14: =COUNTIF(TT!$D$307:$D$319,TALLY!A14) -> 1 | S14: =COUNTIF(TT!$D$326:$D$334,TALLY!A14) -> 0 | T14: =COUNTIF(TT!$D$341:$D$350,TALLY!A14) -> 0 | U14: =COUNTIF(TT!$D$357:$D$366,TALLY!A14) -> 0 | V14: =COUNTIF(TT!$D$373:$D$383,TALLY!A14) -> 0 | W14: =COUNTIF(TT!$D$390:$D$405,TALLY!A14) -> 1 | X14: =COUNTIF(TT!$D$412:$D$423,TALLY!A14) -> 0 | Y14: =COUNTIF(TT!$D$430:$D$438,TALLY!A14) -> 0 | Z14: =COUNTIF(TT!$D$443:$D$457,TALLY!A14) -> 0 | AA14: =COUNTIF(TT!$D$464:$D$474,TALLY!A14) -> 0 | AB14: =COUNTIF(TT!$D$481:$D$494,TALLY!A14) -> 1 | AC14: =COUNTIF(TT!$D$503:$D$522,TALLY!A14) -> 1 | AD14: =COUNTIF(TT!$D$529:$D$541,TALLY!A14) -> 0 | AE14: =COUNTIF(TT!$D$548:$D$561,TALLY!A14) -> 0 | AF14: =COUNTIF(TT!$D$574:$D$584,TALLY!A14) -> 0 | AG14: =COUNTIF(TT!$D$591:$D$601,TALLY!A14) -> 0 | AH14: =COUNTIF(TT!$D$608:$D$619,TALLY!A14) -> 0 | AI14: =COUNTIF(TT!$D$628:$D$647,TALLY!A14) -> 1 | AJ14: =COUNTIF(TT!$D$654:$D$668,TALLY!A14) -> 0 | AK14: =COUNTIF(TT!$D$675:$D$685,TALLY!A14) -> 0 | AL14: =COUNTIF(TT!$D$692:$D$702,TALLY!A14) -> 0 | AM14: =COUNTIF(TT!$D$709:$D$721,TALLY!A14) -> 0 | AN14: =COUNTIF(TT!$D$728:$D$737,TALLY!A14) -> 0 | AO14: =COUNTIF(TT!$D$744:$D$753,TALLY!A14) -> 0 | AP14: =COUNTIF(TT!$D$759:$D$774,TALLY!A14) -> 1 | AQ14: =COUNTIF(TT!$D$781:$D$789,TALLY!A14) -> 0 | AR14: ED1-MARI | AS14: =SUM($B14:$D14) -> 0 | AT14: =SUM(E14:G14) -> 1 | AU14: =SUM(H14:J14) -> 0 | AV14: =SUM(K14:M14) -> 1 | AW14: =SUM(N14:P14) -> 0 | AX14: =SUM($Q14:$S14) -> 1 | AY14: =SUM(T14:V14) -> 0 | AZ14: =SUM(W14:Y14) -> 1 | BA14: =SUM(Z14:AB14) -> 1 | BB14: =SUM(AC14:AE14) -> 1 | BC14: =SUM(AF14:AH14) -> 0 | BD14: =SUM(AI14:AK14) -> 1 | BE14: =SUM(AL14:AN14) -> 0 | BF14: =SUM(AO14:AQ14) -> 1 | BG14: =SUM(AS14:BF14) -> 8
... A74: ED4-TEL | B74: =COUNTIF(TT!$D$6:$D$15,TALLY!A74) -> 0 | C74: =COUNTIF(TT!$D$22:$D$32,TALLY!A74) -> 0 | D74: =COUNTIF(TT!$D$39:$D$49,TALLY!A74) -> 0 | E74: =COUNTIF(TT!$D$57:$D$67,TALLY!A74) -> 1 | F74: =COUNTIF(TT!$D$74:$D$86,TALLY!A74) -> 0 | G74: =COUNTIF(TT!$D$93:$D$107,TALLY!A74) -> 0 | H74: =COUNTIF(TT!$D$113:$D$129,TALLY!A74) -> 0 | I74: =COUNTIF(TT!$D$135:$D$155,TALLY!A74) -> 0 | J74: =COUNTIF(TT!$D$162:$D$173,TALLY!A74) -> 1 | K74: =COUNTIF(TT!$D$180:$D$199,TALLY!A74) -> 0 | L74: =COUNTIF(TT!$D$207:$D$215,TALLY!A74) -> 0 | M74: =COUNTIF(TT!$D$224:$D$231,TALLY!A74) -> 0 | N74: =COUNTIF(TT!$D$237:$D$249,TALLY!A74) -> 0 | O74: =COUNTIF(TT!$D$256:$D$264,TALLY!A74) -> 0 | P74: =COUNTIF(TT!$D$271:$D$286,TALLY!A74) -> 0 | Q74: =COUNTIF(TT!$D$293:$D$300,TALLY!A74) -> 0 | R74: =COUNTIF(TT!$D$307:$D$319,TALLY!A74) -> 0 | S74: =COUNTIF(TT!$D$326:$D$334,TALLY!A74) -> 0 | T74: =COUNTIF(TT!$D$341:$D$350,TALLY!A74) -> 0 | U74: =COUNTIF(TT!$D$357:$D$366,TALLY!A74) -> 1 | V74: =COUNTIF(TT!$D$373:$D$383,TALLY!A74) -> 0 | W74: =COUNTIF(TT!$D$390:$D$405,TALLY!A74) -> 0 | X74: =COUNTIF(TT!$D$412:$D$423,TALLY!A74) -> 0 | Y74: =COUNTIF(TT!$D$430:$D$438,TALLY!A74) -> 0 | Z74: =COUNTIF(TT!$D$443:$D$457,TALLY!A74) -> 0 | AA74: =COUNTIF(TT!$D$464:$D$474,TALLY!A74) -> 0 | AB74: =COUNTIF(TT!$D$481:$D$494,TALLY!A74) -> 0 | AC74: =COUNTIF(TT!$D$503:$D$522,TALLY!A74) -> 0 | AD74: =COUNTIF(TT!$D$529:$D$541,TALLY!A74) -> 0 | AE74: =COUNTIF(TT!$D$548:$D$561,TALLY!A74) -> 0 | AF74: =COUNTIF(TT!$D$574:$D$584,TALLY!A74) -> 0 | AG74: =COUNTIF(TT!$D$591:$D$601,TALLY!A74) -> 0 | AH74: =COUNTIF(TT!$D$608:$D$619,TALLY!A74) -> 1 | AI74: =COUNTIF(TT!$D$628:$D$647,TALLY!A74) -> 0 | AJ74: =COUNTIF(TT!$D$654:$D$668,TALLY!A74) -> 1 | AK74: =COUNTIF(TT!$D$675:$D$685,TALLY!A74) -> 0 | AL74: =COUNTIF(TT!$D$692:$D$702,TALLY!A74) -> 0 | AM74: =COUNTIF(TT!$D$709:$D$721,TALLY!A74) -> 0 | AN74: =COUNTIF(TT!$D$728:$D$737,TALLY!A74) -> 1 | AO74: =COUNTIF(TT!$D$744:$D$753,TALLY!A74) -> 0 | AP74: =COUNTIF(TT!$D$759:$D$774,TALLY!A74) -> 0 | AQ74: =COUNTIF(TT!$D$781:$D$789,TALLY!A74) -> 0 | AR74: ED4-TEL | AS74: =SUM($B74:$D74) -> 0 | AT74: =SUM(E74:G74) -> 1 | AU74: =SUM(H74:J74) -> 1 | AV74: =SUM(K74:M74) -> 0 | AW74: =SUM(N74:P74) -> 0 | AX74: =SUM($Q74:$S74) -> 0 | AY74: =SUM(T74:V74) -> 1 | AZ74: =SUM(W74:Y74) -> 0 | BA74: =SUM(Z74:AB74) -> 0 | BB74: =SUM(AC74:AE74) -> 0 | BC74: =SUM(AF74:AH74) -> 1 | BD74: =SUM(AI74:AK74) -> 1 | BE74: =SUM(AL74:AN74) -> 1 | BF74: =SUM(AO74:AQ74) -> 0 | BG74: =SUM(AS74:BF74) -> 6
A75: Sum | B75: =SUM(B3:B74) -> 10 | C75: =SUM(C3:C74) -> 11 | D75: =SUM(D3:D74) -> 11 | E75: =SUM(E3:E74) -> 11 | F75: =SUM(F3:F74) -> 13 | G75: =SUM(G3:G74) -> 15 | H75: =SUM(H3:H74) -> 17 | I75: =SUM(I3:I74) -> 21 | ... AQ75: =SUM(AQ3:AQ74) -> 9

Sheet WATER

Sheet ROOMS
A1: College of Engineering
A2: Available Rooms
A3: Rooms | B3: Exam Capacity
A4: LT | B4: 50 | C4: COHORT A1 | D4: BAMFO KWAKYE A | E4: 2
A5: RMA | B5: 48 | E5: 1
A6: RMB | B6: 48 | E6: 1
A7: VSLA | B7: 90 | E7: 2 | F7: 474
A8: 206 | B8: 48 | C8: COHORT A2 | E8: 1
A9: 303 | B9: 60 | E9: 2
A10: 304 | B10: 40 | E10: 1
A11: N1 | B11: 50 | C11: COHORT A3 | E11: 1
A12: N2 | B12: 40 | E12: 1
A13: PB001 | B13: 80 | C13: COHORT B1 | D13: PETROLEUM BUILDING B | E13: 2
A14: PB020 | B14: 80 | E14: 2
A15: PB014 | B15: 80 | E15: 2
A16: PB012 | B16: 0 | E16: 1
A17: PB008 | B17: 60 | E17: 2
A18: PB201 | B18: 80 | C18: COHORT B2 | E18: 2
A19: PB214 | B19: 80 | E19: 2
A20: PB212 | B20: 50 | E20: 1
A21: PB208 | B21: 60 | E21: 1 | F21: =SUM(B13:B21) -> 570
A22: VCR | B22: 50 | C22: COHORT C1 | D22: EXAMS OFFICE C | E22: 1
A23: ECR | B23: 50 | E23: 1
A24: A110 | B24: 60 | E24: 2
A25: EA | B25: 60 | C25: COHORT C2 | E25: 3
A26: NAF1 | B26: 90 | E26: 2 | F26: =SUM(B22:B26) -> 310
A27: NEB-SF1 | B27: 160 | C27: COHORT D1 | D27: NEB D | E27: 3
A28: NEB-FF2 | B28: 60 | C28: COHORT D2 | E28: 2
A29: NEB-FF1 | B29: 110 | C29: COHORT D3
A30: NEB-TF | B30: 160 | E30: 2 | F30: =SUM(B27:B30) -> 490
E31: 1
A32: Total | B32: =SUM(B4:B30) -> 1844

Sheet cenG_PROJECT (2nd Sem)

Sheet Invigilation + Meals(2nd Sem)
A1: KWAME NKRUMAH UNIVERSITY OF SCIENCE AND TECHNOLOGY
A2: COLLEGE OF ENGINEERING
A3: END OF FIRST SEMESTER EXAMINATIONS 2024/2025 ACADEMIC YEAR
A4: Invigilation + Meals Reumuneration
A5: SN | B5: STAFF ID | C5: Name | D5: Status | E5: Time/hrs | F5: Rate/Hr | G5: Total Inv. Amount | H5: Meals Amount (GHC) | I5: Amt (GHC) | J5: Tax (GHC) | K5: Amt Due (GHC) | L5: Pay Status
A6: 1 | C6: OSEI TUTU DERRICK | D6: NSM/NSS/pro | E6: 14 | F6: 30 | G6: =E6*F6 -> 420 | H6: 200 | I6: =G6+H6 -> 620 | J6: =I6*0.1 -> 62 | K6: =I6*0.9 -> 558 | L6: CASH | N6: 30 | O6: 10
A7: 2 | C7: DOROTHY AGYEMANG AKUA | D7: NSM/NSS/pro | E7: 14 | F7: 30 | G7: =E7*F7 -> 420 | H7: 200 | I7: =G7+H7 -> 620 | J7: =I7*0.1 -> 62 | K7: =I7*0.9 -> 558 | L7: CASH | N7: 30 | O7: 10
A8: 3 | C8: DUFFOUR JUSTICE | D8: NSM/NSS/pro | E8: 14 | F8: 30 | G8: =E8*F8 -> 420 | H8: 200 | I8: =G8+H8 -> 620 | J8: =I8*0.1 -> 62 | K8: =I8*0.9 -> 558 | L8: CASH | N8: 30 | O8: 10
A9: 4 | C9: BRIGHT AMOAKO WIAFE | D9: NSM/NSS/pro | E9: 14 | F9: 30 | G9: =E9*F9 -> 420 | H9: 200 | I9: =G9+H9 -> 620 | J9: =I9*0.1 -> 62 | K9: =I9*0.9 -> 558 | L9: CASH | N9: 30 | O9: 10
A10: 5 | C10: ERICA TUTUWAA BAFFOE JNR. | D10: NSM/NSS/pro | E10: 14 | F10: 30 | G10: =E10*F10 -> 420 | H10: 200 | I10: =G10+H10 -> 620 | J10: =I10*0.1 -> 62 | K10: =I10*0.9 -> 558 | L10: CASH | N10: 30 | O10: 12
A11: 6 | C11: AARON GYAMFI ATOBRAH APRAKU | D11: NSM/NSS/pro | E11: 14 | F11: 30 | G11: =E11*F11 -> 420 | H11: 200 | I11: =G11+H11 -> 620 | J11: =I11*0.1 -> 62 | K11: =I11*0.9 -> 558 | L11: CASH | N11: 30 | O11: 12
A12: 7 | C12: AMPONSAH MICHAEL DARKO | D12: NSM/NSS/pro | E12: 14 | F12: 30 | G12: =E12*F12 -> 420 | H12: 200 | I12: =G12+H12 -> 620 | J12: =I12*0.1 -> 62 | K12: =I12*0.9 -> 558 | L12: CASH | N12: 30 | O12: 15
A13: 8 | C13: GIDEON SAKYI OSEW | D13: NSM/NSS/pro | E13: 14 | F13: 30 | G13: =E13*F13 -> 420 | H13: 200 | I13: =G13+H13 -> 620 | J13: =I13*0.1 -> 62 | K13: =I13*0.9 -> 558 | L13: CASH
A14: 9 | C14: KWABENA AFAAWUAH | D14: NSM/NSS/Acct | E14: 18 | F14: 30 | G14: =E14*F14 -> 540 | H14: 200 | I14: =G14+H14 -> 740 | J14: =I14*0.1 -> 74 | K14: =I14*0.9 -> 666 | L14: CASH
A15: 10 | C15: CLIFF OBIRI SEPAH | D15: NSM/NSS/Acct | E15: 25 | F15: 30 | G15: =E15*F15 -> 750 | H15: 200 | I15: =G15+H15 -> 950 | J15: =I15*0.1 -> 95 | K15: =I15*0.9 -> 855 | L15: CASH
A16: 11 | C16: BAAH-BOATENG SAMUEL | D16: NSM/NSS/Acct | E16: 18 | F16: 30 | G16: =E16*F16 -> 540 | H16: 200 | I16: =G16+H16 -> 740 | J16: =I16*0.1 -> 74 | K16: =I16*0.9 -> 666 | L16: CASH
A17: 12 | C17: NANA AGYEMANG AMOAHENE YEBOAH | D17: NSM/NSS/Audit | E17: 80 | F17: 30 | G17: =E17*F17 -> 2400 | H17: 400 | I17: =G17+H17 -> 2800 | J17: =I17*0.1 -> 280 | K17: =I17*0.9 -> 2520 | L17: CASH
A18: 13 | C18: CHRISTIAN D. BOATENG | D18: NSM/NSS/pro | E18: 30 | F18: =N18 -> 30 | G18: =E18*F18 -> 900 | H18: 200 | I18: =G18+H18 -> 1100 | J18: =I18*0.1 -> 110 | K18: =I18*0.9 -> 990 | L18: CASH | N18: 30 | O18: 10
A19: 14 | C19: JONATHAN AGYEMAN-DUAH KARIKARI | D19: SS/procur | E19: 80 | F19: =N19 -> 30 | G19: =E19*F19 -> 2400 | H19: 400 | I19: =G19+H19 -> 2800 | J19: =I19*0.1 -> 280 | K19: =I19*0.9 -> 2520 | L19: CASH | N19: 30 | O19: 12
A20: 15 | C20: IMBEAH JULIET | D20: NSM/NSS-TA-wt | E20: 75 | F20: =N20 -> 30 | G20: =E20*F20 -> 2250 | H20: 300 | I20: =G20+H20 -> 2550 | J20: =I20*0.1 -> 255 | K20: =I20*0.9 -> 2295 | L20: CASH | N20: 30
A21: 16 | C21: RUTH ATTA BENYAH | D21: NSM/NSS-TA-wt | E21: 75 | F21: =N21 -> 30 | G21: =E21*F21 -> 2250 | H21: 300 | I21: =G21+H21 -> 2550 | J21: =I21*0.1 -> 255 | K21: =I21*0.9 -> 2295 | L21: CASH | N21: 30
A22: 17 | C22: PAUL ADAZURU | D22: NSM/NSS-TA-wt | E22: 75 | F22: =N22 -> 30 | G22: =E22*F22 -> 2250 | H22: 300 | I22: =G22+H22 -> 2550 | J22: =I22*0.1 -> 255 | K22: =I22*0.9 -> 2295 | L22: CASH | N22: 30
A23: 18 | C23: OMANHENE KOFI GYIMAH | D23: NSM/NSS-TA-wt | E23: 75 | F23: 30 | G23: =E23*F23 -> 2250 | H23: 300 | I23: =G23+H23 -> 2550 | J23: =I23*0.1 -> 255 | K23: =I23*0.9 -> 2295 | L23: CASH | N23: 30
A24: 19 | C24: GARVIN KOKONU | D24: NSM/NSS-TA-wt | E24: 75 | F24: 30 | G24: =E24*F24 -> 2250 | H24: 300 | I24: =G24+H24 -> 2550 | J24: =I24*0.1 -> 255 | K24: =I24*0.9 -> 2295 | L24: CASH | N24: 30
A25: 20 | C25: MARY ADDAI | D25: NSM/NSS-nurs | E25: 130 | F25: =N25 -> 30 | G25: =E25*F25 -> 3900 | H25: 500 | I25: =G25+H25 -> 4400 | J25: =I25*0.1 -> 440 | K25: =I25*0.9 -> 3960 | L25: CASH | N25: 30 | O25: 55
A26: 21 | C26: VIVIAN DZAKA | D26: NSM/NSS-nurs | E26: 130 | F26: =N26 -> 30 | G26: =E26*F26 -> 3900 | H26: 500 | I26: =G26+H26 -> 4400 | J26: =I26*0.1 -> 440 | K26: =I26*0.9 -> 3960 | L26: CASH | N26: 30
A27: 22 | C27: Abdul-Mumin Tahiru | D27: NSM/NSS-TA | E27: 11 | F27: 30 | G27: =E27*F27 -> 330 | H27: =E27*10 -> 110 | I27: =G27+H27 -> 440 | J27: =0.1*I27 -> 44 | K27: =0.9*I27 -> 396 | L27: CASH | N27: 30 | O27: 55
A28: 23 | C28: Polycarp Bome | D28: NSM/NSS-TA | E28: 11 | F28: 30 | G28: =E28*F28 -> 330 | H28: =E28*10 -> 110 | I28: =G28+H28 -> 440 | J28: =0.1*I28 -> 44 | K28: =0.9*I28 -> 396 | L28: CASH | N28: 30 | O28: 55 | P28: 15
A29: 24 | C29: Akambisa Julius | D29: NSM/NSS-TA | E29: 9 | F29: 30 | G29: =E29*F29 -> 270 | H29: =E29*10 -> 90 | I29: =G29+H29 -> 360 | J29: =0.1*I29 -> 36 | K29: =0.9*I29 -> 324 | L29: CASH | N29: 30 | O29: 62
A30: 25 | C30: Adu Isaac Kwabena Afriyie | D30: NSM/NSS-TA | E30: 9 | F30: 30 | G30: =E30*F30 -> 270 | H30: =E30*10 -> 90 | I30: =G30+H30 -> 360 | J30: =0.1*I30 -> 36 | K30: =0.9*I30 -> 324 | L30: CASH | N30: 30 | O30: 62
A31: 26 | C31: Amissah Nana Ama | D31: NSM/NSS-TA | E31: 9 | F31: 30 | G31: =E31*F31 -> 270 | H31: =E31*10 -> 90 | I31: =G31+H31 -> 360 | J31: =0.1*I31 -> 36 | K31: =0.9*I31 -> 324 | L31: CASH | N31: 30 | O31: 62
A32: 27 | C32: Akowuah Nana Amoah | D32: NSM/NSS-TA | E32: 9 | F32: 30 | G32: =E32*F32 -> 270 | H32: =E32*10 -> 90 | I32: =G32+H32 -> 360 | J32: =0.1*I32 -> 36 | K32: =0.9*I32 -> 324 | L32: CASH | N32: 30 | O32: 10
A33: 28 | C33: Ankomah Theophilus | D33: NSM/NSS-TA | E33: 11 | F33: 30 | G33: =E33*F33 -> 330 | H33: =E33*10 -> 110 | I33: =G33+H33 -> 440 | J33: =0.1*I33 -> 44 | K33: =0.9*I33 -> 396 | L33: CASH | N33: 30 | O33: 9
A34: 29 | C34: Antwi Dennis Barima | D34: NSM/NSS-TA | E34: 6 | F34: 30 | G34: =E34*F34 -> 180 | H34: =E34*10 -> 60 | I34: =G34+H34 -> 240 | J34: =0.1*I34 -> 24 | K34: =0.9*I34 -> 216 | L34: CASH | N34: 30
A35: 30 | C35: Dzah Raymond | D35: NSM/NSS-TA | E35: 11 | F35: 30 | G35: =E35*F35 -> 330 | H35: =E35*10 -> 110 | I35: =G35+H35 -> 440 | J35: =0.1*I35 -> 44 | K35: =0.9*I35 -> 396 | L35: CASH | N35: 30 | O35: 15
A36: 31 | C36: Dadzie Emmanuel | D36: NSM/NSS-TA | E36: 9 | F36: 30 | G36: =E36*F36 -> 270 | H36: =E36*10 -> 90 | I36: =G36+H36 -> 360 | J36: =0.1*I36 -> 36 | K36: =0.9*I36 -> 324 | L36: CASH | N36: 30 | O36: 11
A37: 32 | C37: Egyir Bernard | D37: NSM/NSS-TA | E37: 9 | F37: 30 | G37: =E37*F37 -> 270 | H37: =E37*10 -> 90 | I37: =G37+H37 -> 360 | J37: =0.1*I37 -> 36 | K37: =0.9*I37 -> 324 | L37: CASH | N37: 30 | O37: 21
A38: 33 | C38: Ekuful Ebenezer | D38: NSM/NSS-TA | E38: 18 | F38: 30 | G38: =E38*F38 -> 540 | H38: =E38*10 -> 180 | I38: =G38+H38 -> 720 | J38: =0.1*I38 -> 72 | K38: =0.9*I38 -> 648 | L38: CASH | N38: 30
A39: 34 | C39: Felix Owiredu Owusu | D39: NSM/NSS-TA | E39: 11 | F39: 30 | G39: =E39*F39 -> 330 | H39: =E39*10 -> 110 | I39: =G39+H39 -> 440 | J39: =0.1*I39 -> 44 | K39: =0.9*I39 -> 396 | L39: CASH | N39: 30 | O39: 14
A40: 35 | C40: George Nii Martey Colley | D40: NSM/NSS-TA | E40: 11 | F40: 30 | G40: =E40*F40 -> 330 | H40: =E40*10 -> 110 | I40: =G40+H40 -> 440 | J40: =0.1*I40 -> 44 | K40: =0.9*I40 -> 396 | L40: CASH | N40: 30 | O40: 10
A41: 36 | C41: Immanuel Yeboah Anomah | D41: NSM/NSS-TA | E41: 11 | F41: 30 | G41: =E41*F41 -> 330 | H41: =E41*10 -> 110 | I41: =G41+H41 -> 440 | J41: =0.1*I41 -> 44 | K41: =0.9*I41 -> 396 | L41: CASH | N41: 30 | O41: 11
A42: 37 | C42: Isaac Adu | D42: NSM/NSS-TA | E42: 9 | F42: 30 | G42: =E42*F42 -> 270 | H42: =E42*10 -> 90 | I42: =G42+H42 -> 360 | J42: =0.1*I42 -> 36 | K42: =0.9*I42 -> 324 | L42: CASH | N42: 30 | O42: 10
A43: 38 | C43: Isaac Clottey | D43: NSM/NSS-TA | E43: 14 | F43: 30 | G43: =E43*F43 -> 420 | H43: =E43*10 -> 140 | I43: =G43+H43 -> 560 | J43: =0.1*I43 -> 56 | K43: =0.9*I43 -> 504 | L43: CASH | N43: 30 | O43: 8
A44: 39 | C44: Jeremiah Dodzi Cofie | D44: NSM/NSS-TA | E44: 9 | F44: 30 | G44: =E44*F44 -> 270 | H44: =E44*10 -> 90 | I44: =G44+H44 -> 360 | J44: =0.1*I44 -> 36 | K44: =0.9*I44 -> 324 | L44: CASH | N44: 30 | O44: 6
A45: 40 | C45: Jibril Aligabass | D45: NSM/NSS-TA | E45: 11 | F45: 30 | G45: =E45*F45 -> 330 | H45: =E45*10 -> 110 | I45: =G45+H45 -> 440 | J45: =0.1*I45 -> 44 | K45: =0.9*I45 -> 396 | L45: CASH | N45: 30 | O45: 8
A46: 41 | C46: Owusu Binfoh Romeo | D46: NSM/NSS-TA | E46: 31 | F46: 30 | G46: =E46*F46 -> 930 | H46: =E46*10 -> 310 | I46: =G46+H46 -> 1240 | J46: =0.1*I46 -> 124 | K46: =0.9*I46 -> 1116 | L46: CASH | N46: 30 | O46: 8
A47: 42 | C47: Priscilla Adwoa Fordjour | D47: NSM/NSS-TA | E47: 17 | F47: 30 | G47: =E47*F47 -> 510 | H47: =E47*10 -> 170 | I47: =G47+H47 -> 680 | J47: =0.1*I47 -> 68 | K47: =0.9*I47 -> 612 | L47: CASH | N47: 30 | O47: 8
A48: 43 | C48: Solomon Appiah-Gyamfi | D48: NSM/NSS-TA | E48: 15 | F48: 30 | G48: =E48*F48 -> 450 | H48: =E48*10 -> 150 | I48: =G48+H48 -> 600 | J48: =0.1*I48 -> 60 | K48: =0.9*I48 -> 540 | L48: CASH | N48: 30 | O48: 8
A49: 44 | C49: Stephen Onomah | D49: NSM/NSS-TA | E49: 12 | F49: 30 | G49: =E49*F49 -> 360 | H49: =E49*10 -> 120 | I49: =G49+H49 -> 480 | J49: =0.1*I49 -> 48 | K49: =0.9*I49 -> 432 | L49: CASH | N49: 30 | O49: 8
A50: 45 | C50: Theophilus Nyarko | D50: NSM/NSS-TA | E50: 9 | F50: 30 | G50: =E50*F50 -> 270 | H50: =E50*10 -> 90 | I50: =G50+H50 -> 360 | J50: =0.1*I50 -> 36 | K50: =0.9*I50 -> 324 | L50: CASH | N50: 30 | O50: 7
... A58: 53 | C58: ABAGRE MAJEED WINIMI | D58: NSM/NSS-TA | E58: 9 | F58: 30 | G58: =E58*F58 -> 270 | H58: =E58*10 -> 90 | I58: =G58+H58 -> 360 | J58: =0.1*I58 -> 36 | K58: =0.9*I58 -> 324 | L58: CASH | N58: 30 | O58: 6
A59: 54 | C59: ABDUL-BASIT NUHU | D59: NSM/NSS-TA | E59: 11 | F59: 30 | G59: =E59*F59 -> 330 | H59: =E59*10 -> 110 | I59: =G59+H59 -> 440 | J59: =0.1*I59 -> 44 | K59: =0.9*I59 -> 396 | L59: CASH | N59: 30
A60: 55 | C60: ABIGAIL ANKU | D60: NSM/NSS-TA | E60: 10 | F60: 30 | G60: =E60*F60 -> 300 | H60: =E60*10 -> 100 | I60: =G60+H60 -> 400 | J60: =0.1*I60 -> 40 | K60: =0.9*I60 -> 360 | L60: CASH | N60: 30 | O60: 35
A61: 56 | C61: Diabene Yaw Addo | D61: NSM/NSS-TA | E61: 9 | F61: 30 | G61: =E61*F61 -> 270 | H61: =E61*10 -> 90 | I61: =G61+H61 -> 360 | J61: =0.1*I61 -> 36 | K61: =0.9*I61 -> 324 | L61: CASH | N61: 30 | O61: 35
A62: 57 | C62: AGBE SETORDZI GAMELI | D62: NSM/NSS-TA | E62: 11 | F62: 30 | G62: =E62*F62 -> 330 | H62: =E62*10 -> 110 | I62: =G62+H62 -> 440 | J62: =0.1*I62 -> 44 | K62: =0.9*I62 -> 396 | L62: CASH | N62: 30 | O62: 25
A63: 58 | C63: AGBLEMIAWO MARVIN SELASI | D63: NSM/NSS-TA | E63: 8 | F63: 30 | G63: =E63*F63 -> 240 | H63: =E63*10 -> 80 | I63: =G63+H63 -> 320 | J63: =0.1*I63 -> 32 | K63: =0.9*I63 -> 288 | L63: CASH | N63: 30 | O63: 25
A64: 59 | C64: AGYAPONG AKOSUA ADUBEA | D64: NSM/NSS-TA | E64: 9 | F64: 30 | G64: =E64*F64 -> 270 | H64: =E64*10 -> 90 | I64: =G64+H64 -> 360 | J64: =0.1*I64 -> 36 | K64: =0.9*I64 -> 324 | L64: CASH | N64: 30 | O64: 25
A65: 60 | C65: AGYAPONG DORCAS NUANIAH | D65: NSM/NSS-TA | E65: 26 | F65: 30 | G65: =E65*F65 -> 780 | H65: =E65*10 -> 260 | I65: =G65+H65 -> 1040 | J65: =0.1*I65 -> 104 | K65: =0.9*I65 -> 936 | L65: CASH | N65: 30 | O65: 25
A66: 61 | C66: AGYEMANG DUKU RISMOND | D66: NSM/NSS-TA | E66: 9 | F66: 30 | G66: =E66*F66 -> 270 | H66: =E66*10 -> 90 | I66: =G66+H66 -> 360 | J66: =0.1*I66 -> 36 | K66: =0.9*I66 -> 324 | L66: CASH | N66: 30 | O66: 25
A67: 62 | C67: ALHASSAN ABDUL GANIYU | D67: NSM/NSS-TA | E67: 11 | F67: 30 | G67: =E67*F67 -> 330 | H67: =E67*10 -> 110 | I67: =G67+H67 -> 440 | J67: =0.1*I67 -> 44 | K67: =0.9*I67 -> 396 | L67: CASH | N67: 30 | O67: 25
A68: 63 | C68: ALHASSAN MUBARIK | D68: NSM/NSS-TA | E68: 9 | F68: 30 | G68: =E68*F68 -> 270 | H68: =E68*10 -> 90 | I68: =G68+H68 -> 360 | J68: =0.1*I68 -> 36 | K68: =0.9*I68 -> 324 | L68: CASH | N68: 30 | O68: 25
A69: 64 | C69: ALI MUHAISIN | D69: NSM/NSS-TA | E69: 9 | F69: 30 | G69: =E69*F69 -> 270 | H69: =E69*10 -> 90 | I69: =G69+H69 -> 360 | J69: =0.1*I69 -> 36 | K69: =0.9*I69 -> 324 | L69: CASH | N69: 30 | O69: 25
A70: 65 | C70: ANITA DOKUWAH NYARKO | D70: NSM/NSS-TA | E70: 17 | F70: 30 | G70: =E70*F70 -> 510 | H70: =E70*10 -> 170 | I70: =G70+H70 -> 680 | J70: =0.1*I70 -> 68 | K70: =0.9*I70 -> 612 | L70: CASH | N70: 30 | O70: 25
A71: 66 | C71: AZUNGU BENJAMIN | D71: NSM/NSS-TA | E71: 8 | F71: 30 | G71: =E71*F71 -> 240 | H71: =E71*10 -> 80 | I71: =G71+H71 -> 320 | J71: =0.1*I71 -> 32 | K71: =0.9*I71 -> 288 | L71: CASH | N71: 30 | O71: 25
... A132: 127 | C132: NANA KWEKU AMISSAH | D132: NSM/NSS-TA | E132: 8 | F132: 30 | G132: =E132*F132 -> 240 | H132: =E132*10 -> 80 | I132: =G132+H132 -> 320 | J132: =0.1*I132 -> 32 | K132: =0.9*I132 -> 288 | L132: CASH | N132: 30 | O132: 25
A133: 128 | C133: NATHANIEL FOLI | D133: NSM/NSS-TA | E133: 11 | F133: 30 | G133: =E133*F133 -> 330 | H133: 115 | I133: 440 | J133: =0.1*I133 -> 44 | K133: =0.9*I133 -> 396 | L133: CASH | N133: 30 | O133: 25
A134: 129 | C134: NYARKO PRINCE | D134: NSM/NSS-TA | E134: 9 | F134: 30 | G134: =E134*F134 -> 270 | H134: =E134*10 -> 90 | I134: =G134+H134 -> 360 | J134: =0.1*I134 -> 36 | K134: =0.9*I134 -> 324 | L134: CASH | N134: 30 | O134: 25
A135: 130 | C135: OBENG BENJAMIN | D135: NSM/NSS-TA | E135: 9 | F135: 30 | G135: =E135*F135 -> 270 | H135: =E135*10 -> 90 | I135: =G135+H135 -> 360 | J135: =0.1*I135 -> 36 | K135: =0.9*I135 -> 324 | L135: CASH | N135: 30 | O135: 25
A136: 131 | C136: OFORI ROCKSON MINKAH | D136: NSM/NSS-TA | E136: 8 | F136: 30 | G136: =E136*F136 -> 240 | H136: =E136*10 -> 80 | I136: =G136+H136 -> 320 | J136: =0.1*I136 -> 32 | K136: =0.9*I136 -> 288 | L136: CASH | N136: 30 | O136: 25
A137: 132 | C137: OKOE FELIX KOJO RANDY | D137: NSM/NSS-TA | E137: 11 | F137: 30 | G137: =E137*F137 -> 330 | H137: =E137*10 -> 110 | I137: =G137+H137 -> 440 | J137: =0.1*I137 -> 44 | K137: =0.9*I137 -> 396 | L137: CASH | N137: 30 | O137: 25
A138: 133 | C138: OSEI AMANIAMPONG HENRY MANASSEH | D138: NSM/NSS-TA | E138: 11 | F138: 30 | G138: =E138*F138 -> 330 | H138: =E138*10 -> 110 | I138: =G138+H138 -> 440 | J138: =0.1*I138 -> 44 | K138: =0.9*I138 -> 396 | L138: CASH | N138: 30 | O138: 25
A139: 134 | C139: OSUMANU RABIATU | D139: NSM/NSS-TA | E139: 9 | F139: 30 | G139: =E139*F139 -> 270 | H139: =E139*10 -> 90 | I139: =G139+H139 -> 360 | J139: =0.1*I139 -> 36 | K139: =0.9*I139 -> 324 | L139: CASH | N139: 30 | O139: 25
A140: 135 | C140: OWIREDU-GHORMAN EWURAMA OWIREDUWAA | D140: NSM/NSS-TA | E140: 9 | F140: 30 | G140: =E140*F140 -> 270 | H140: =E140*10 -> 90 | I140: =G140+H140 -> 360 | J140: =0.1*I140 -> 36 | K140: =0.9*I140 -> 324 | L140: CASH | N140: 30 | O140: 25
A141: 136 | C141: OWUSU BOAKYE GIDEON | D141: NSM/NSS-TA | E141: 8 | F141: 30 | G141: =E141*F141 -> 240 | H141: =E141*10 -> 80 | I141: =G141+H141 -> 320 | J141: =0.1*I141 -> 32 | K141: =0.9*I141 -> 288 | L141: CASH | N141: 30 | O141: 25
A142: 137 | C142: PHILIP DARKO | D142: NSM/NSS-TA | E142: 11 | F142: 30 | G142: =E142*F142 -> 330 | H142: =E142*10 -> 110 | I142: =G142+H142 -> 440 | J142: =0.1*I142 -> 44 | K142: =0.9*I142 -> 396 | L142: CASH | N142: 30 | O142: 25
A143: 138 | C143: PHILIP KOJO ANSAH | D143: NSM/NSS-TA | E143: 9 | F143: 30 | G143: =E143*F143 -> 270 | H143: =E143*10 -> 90 | I143: =G143+H143 -> 360 | J143: =0.1*I143 -> 36 | K143: =0.9*I143 -> 324 | L143: CASH | N143: 30 | O143: 25
A144: 139 | C144: POKU ATTA ANDY | D144: NSM/NSS-TA | E144: 12 | F144: 30 | G144: =E144*F144 -> 360 | H144: =E144*10 -> 120 | I144: =G144+H144 -> 480 | J144: =0.1*I144 -> 48 | K144: =0.9*I144 -> 432 | L144: CASH | N144: 30 | O144: 25
A145: 140 | C145: PRINCE DAWSON TETTEH | D145: NSM/NSS-TA | E145: 9 | F145: 30 | G145: =E145*F145 -> 270 | H145: =E145*10 -> 90 | I145: =G145+H145 -> 360 | J145: =0.1*I145 -> 36 | K145: =0.9*I145 -> 324 | L145: CASH | N145: 30 | O145: 25
... A186: 181 | C186: Ohene Lawrencia | D186: NSM/NSS-TA | E186: 14 | F186: 30 | G186: =E186*F186 -> 420 | H186: =E186*10 -> 140 | I186: =G186+H186 -> 560 | J186: =0.1*I186 -> 56 | K186: =0.9*I186 -> 504 | L186: CASH | N186: 30 | O186: 29
A187: 182 | C187: ENOCK ANNOR BOYE | D187: NSM/biom | E187: 48 | F187: =N187 -> 30 | G187: =E187*F187 -> 1440 | H187: 360 | I187: =G187+H187 -> 1800 | J187: =I187*0.1 -> 180 | K187: =I187*0.9 -> 1620 | L187: CASH | N187: 30
A188: 183 | C188: OSCAR OUSSENI OUEDRAOGO | D188: NSM/biom | E188: 50 | F188: =N188 -> 30 | G188: =E188*F188 -> 1500 | H188: 375 | I188: =G188+H188 -> 1875 | J188: =I188*0.1 -> 187.5 | K188: =I188*0.9 -> 1687.5 | L188: CASH | N188: 30
A189: 184 | C189: EDEM EDWIN ADEDZE | D189: NSM/biom | E189: 50 | F189: =N189 -> 30 | G189: =E189*F189 -> 1500 | H189: 375 | I189: =G189+H189 -> 1875 | J189: =I189*0.1 -> 187.5 | K189: =I189*0.9 -> 1687.5 | L189: CASH | N189: 30
A190: 185 | C190: JONATHAN KOFI ATIVOR | D190: NSM/biom | E190: 50 | F190: =N190 -> 30 | G190: =E190*F190 -> 1500 | H190: 375 | I190: =G190+H190 -> 1875 | J190: =I190*0.1 -> 187.5 | K190: =I190*0.9 -> 1687.5 | L190: CASH | N190: 30
A191: 186 | C191: DEBORAH ADOM KORANTENG | D191: NSM/biom | E191: 50 | F191: =N191 -> 30 | G191: =E191*F191 -> 1500 | H191: 375 | I191: =G191+H191 -> 1875 | J191: =I191*0.1 -> 187.5 | K191: =I191*0.9 -> 1687.5 | L191: CASH | N191: 30
A192: 187 | C192: JONATHAN NIKOI KOTEY | D192: NSM/biom | E192: 48 | F192: =N192 -> 30 | G192: =E192*F192 -> 1440 | H192: 360 | I192: =G192+H192 -> 1800 | J192: =I192*0.1 -> 180 | K192: =I192*0.9 -> 1620 | L192: CASH | N192: 30
A193: 188 | C193: WILLIAMS OWUSU DARKO | D193: NSM/biom | E193: 50 | F193: =N193 -> 30 | G193: =E193*F193 -> 1500 | H193: 375 | I193: =G193+H193 -> 1875 | J193: =I193*0.1 -> 187.5 | K193: =I193*0.9 -> 1687.5 | L193: CASH | N193: 30
A194: 189 | C194: GENTLE TWUMASI ANKRAH | D194: NSM/biom | E194: 48 | F194: =N194 -> 30 | G194: =E194*F194 -> 1440 | H194: 360 | I194: =G194+H194 -> 1800 | J194: =I194*0.1 -> 180 | K194: =I194*0.9 -> 1620 | L194: CASH | N194: 30
A195: 190 | C195: FOSTER OPOKU | D195: NSM/biom | E195: 46 | F195: =N195 -> 30 | G195: =E195*F195 -> 1380 | H195: 345 | I195: =G195+H195 -> 1725 | J195: =I195*0.1 -> 172.5 | K195: =I195*0.9 -> 1552.5 | L195: CASH | N195: 30
A196: 191 | C196: KOFI YEBOAH ASIEDU-BINEY | D196: NSM/biom | E196: 48 | F196: =N196 -> 30 | G196: =E196*F196 -> 1440 | H196: 360 | I196: =G196+H196 -> 1800 | J196: =I196*0.1 -> 180 | K196: =I196*0.9 -> 1620 | L196: CASH | N196: 30
A197: 192 | C197: GIDEON ATUAHENE | D197: NSM/biom | E197: 50 | F197: =N197 -> 30 | G197: =E197*F197 -> 1500 | H197: 375 | I197: =G197+H197 -> 1875 | J197: =I197*0.1 -> 187.5 | K197: =I197*0.9 -> 1687.5 | L197: CASH | N197: 30
A198: 193 | C198: JUSTICE ASARE KWAKYE | D198: NSM/biom | E198: 50 | F198: =N198 -> 30 | G198: =E198*F198 -> 1500 | H198: 375 | I198: =G198+H198 -> 1875 | J198: =I198*0.1 -> 187.5 | K198: =I198*0.9 -> 1687.5 | L198: CASH | N198: 30
... A212: 207 | C212: IDDRIS PENNAH | D212: NSM/biom | E212: 48 | F212: =N212 -> 30 | G212: =E212*F212 -> 1440 | H212: 360 | I212: =G212+H212 -> 1800 | J212: =I212*0.1 -> 180 | K212: =I212*0.9 -> 1620 | L212: CASH | N212: 30
A213: 208 | C213: ACQUAH FAUSTINE DARLINGTON | D213: NSM/biom | E213: 60 | F213: 30 | G213: =E213*F213 -> 1800 | H213: 375 | I213: =G213+H213 -> 2175 | J213: =I213*0.1 -> 217.5 | K213: =I213*0.9 -> 1957.5 | L213: CASH
A214: 209 | C214: RICHARD GBENNEH | D214: NSM/biom | E214: 62 | F214: 30 | G214: =E214*F214 -> 1860 | H214: 390 | I214: =G214+H214 -> 2250 | J214: =I214*0.1 -> 225 | K214: =I214*0.9 -> 2025 | L214: CASH
A215: 210 | C215: OHENEBA KWAKU ANOKYE MANU | D215: NSM/biom | E215: 40 | F215: =N215 -> 30 | G215: =E215*F215 -> 1200 | H215: 300 | I215: =G215+H215 -> 1500 | J215: =I215*0.1 -> 150 | K215: =I215*0.9 -> 1350 | L215: CASH | N215: 30
A216: 211 | C216: KINGSLEY BOADU BAIDOO | D216: NSM/biom | E216: 50 | F216: =N216 -> 30 | G216: =E216*F216 -> 1500 | H216: 375 | I216: =G216+H216 -> 1875 | J216: =I216*0.1 -> 187.5 | K216: =I216*0.9 -> 1687.5 | L216: CASH | N216: 30
A217: 212 | C217: JOSEPH ROBERT AMPONSAH | D217: NSM/biom | E217: 50 | F217: =N217 -> 30 | G217: =E217*F217 -> 1500 | H217: 375 | I217: =G217+H217 -> 1875 | J217: =I217*0.1 -> 187.5 | K217: =I217*0.9 -> 1687.5 | L217: CASH | N217: 30
A218: 213 | C218: ERIC MINTAH | D218: SS/biom | E218: 110 | F218: =N218 -> 30 | G218: =E218*F218 -> 3300 | H218: 500 | I218: =G218+H218 -> 3800 | J218: =I218*0.1 -> 380 | K218: =I218*0.9 -> 3420 | L218: CASH | N218: 30
A219: 214 | C219: FOSTER SEDEM DEDUME | D219: SM/biom | E219: 80 | F219: 60 | G219: =E219*F219 -> 4800 | H219: 500 | I219: =G219+H219 -> 5300 | J219: =I219*0.1 -> 530 | K219: =I219*0.9 -> 4770 | L219: CASH
A220: 215 | C220: ISAAC ASENSO | D220: SS/biom | E220: 110 | F220: 30 | G220: =E220*F220 -> 3300 | H220: 500 | I220: =G220+H220 -> 3800 | J220: =I220*0.1 -> 380 | K220: =I220*0.9 -> 3420 | L220: CASH
...

Sheet supp
A1: KWAME NKRUMAH UNIVERSITY OF SCIENCE AND TECHNOLOGY
A2: COLLEGE OF ENGINEERING
A3: END OF FIRST SEMESTER EXAMINATIONS 2024/2025 ACADEMIC YEAR
A4: Invigilation + Meals Reumuneration
A6: SN | B6: Name | C6: Status | D6: Time/hrs | E6: Rate/Hr | F6: Total Inv. Amount | G6: Meals Amount (GHC) | H6: Amt (GHC) | I6: Tax (GHC) | J6: Amt Due (GHC) | K6: Pay Status
A7: 1 | B7: NYARKO, KWABENA BIRITWUM | C7: SM | D7: 195 | E7: 60 | F7: =D7*E7 -> 11700 | G7: 600 | H7: =F7+G7 -> 12300 | I7: =H7*0.1 -> 1230 | J7: =H7-I7 -> 11070 | K7: PAYROLL
A8: 2 | B8: Ida Saeed | C8: SM | D8: 130 | E8: 60 | F8: =D8*E8 -> 7800 | G8: 500 | H8: =F8+G8 -> 8300 | I8: =H8*0.1 -> 830 | J8: =H8-I8 -> 7470 | K8: PAYROLL
A9: 3 | B9: OWUSU, JOHNSON | C9: SM | D9: 130 | E9: 60 | F9: =D9*E9 -> 7800 | G9: 500 | H9: =F9+G9 -> 8300 | I9: =H9*0.1 -> 830 | J9: =H9-I9 -> 7470 | K9: PAYROLL
A10: 4 | B10: EMMANUEL ASUMING FRIMPONG | C10: SM/Dean | D10: 148 | E10: 60 | F10: =D10*E10 -> 8880 | G10: 600 | H10: =F10+G10 -> 9480 | I10: =H10*0.1 -> 948 | J10: =H10-I10 -> 8532 | K10: PAYROLL
A11: 5 | B11: KEMAUSOUR FRANCIS | C11: SM/Dean | D11: 148 | E11: 60 | F11: =D11*E11 -> 8880 | G11: 600 | H11: =F11+G11 -> 9480 | I11: =H11*0.1 -> 948 | J11: =H11-I11 -> 8532 | K11: PAYROLL
A12: 6 | B12: ADJEI, KWAKU AMANING | C12: SM/Dean | D12: 148 | E12: 60 | F12: =D12*E12 -> 8880 | G12: 600 | H12: =F12+G12 -> 9480 | I12: =H12*0.1 -> 948 | J12: =H12-I12 -> 8532 | K12: PAYROLL
E13: Total (GHS) | H13: =SUM(H7:H12) -> 57340 | I13: =SUM(I7:I12) -> 5734 | J13: =SUM(J7:J12) -> 51606
B14: `
